Workbook
Name FromArray_1: _xlfn.ANCHORARRAY('Analysis & Diagnostics'!$N$421)
Name Slicer_month: #N/A
Name Slicer_month1: #N/A
Name Slicer_transaction: #N/A
Name Slicer_transaction1: #N/A
Name Slicer_transaction2: #N/A
Name Slicer_transaction3: #N/A
Name Slicer_transaction4: #N/A
Name Slicer_year: #N/A
Name Slicer_year1: #N/A

Sheet Dashboard
A1: Navigate: | B1: Dashboard | C1: Findings | D1: Pivot & Derived Tables | E1: Analysis & Diagnosis | F1: Data Visualization | G1: Cleaned Data Source | H1: Raw Data Source
A2: Key Performance Indicator (KPI)
A4: =_xlfn.CONCAT(ROUND(Table414[[#This Row],[Growth Rate]]* 100, 2), "%") -> -4.21% | C4: =_xlfn.CONCAT(ROUND('Analysis & Diagnostics'!E5* 100, 2), "%") -> -48.71% | F4: =_xlfn.CONCAT(ROUND('Analysis & Diagnostics'!E6* 100, 2), "%") -> -78.16%
A5: =_xlfn.CONCAT("₱ ", TEXT(ROUND('Analysis & Diagnostics'!C4, 2), "###,###.##")) -> ₱ 17,122.6 | C5: =_xlfn.CONCAT("₱ ", TEXT(ROUND(Table414[[#This Row],[Monthly Average]], 2), "###,###.##")) -> ₱ 36,427.47 | F5: =_xlfn.CONCAT("₱ ", TEXT(ROUND('Analysis & Diagnostics'!C6, 2), "###,###.##")) -> ₱ 21,273.87
A6: =_xlfn.CONCAT("₱ ", TEXT(ROUND('Analysis & Diagnostics'!D4, 2), "###,###")) -> ₱ 17,583 | C6: =_xlfn.CONCAT("₱ ", TEXT(ROUND('Analysis & Diagnostics'!D5, 2), "###,###")) -> ₱ 30,278 | F6: =_xlfn.CONCAT("₱ ", TEXT(ROUND('Analysis & Diagnostics'!D6, 2), "###,###")) -> ₱ 15,819
A7: =_xlfn.CONCAT("₱ ",TEXT(ROUND('Analysis & Diagnostics'!B4,2),"###,###")) -> ₱ 256,839 | C7: =_xlfn.CONCAT("₱ ",TEXT(ROUND('Analysis & Diagnostics'!B5,2),"###,###")) -> ₱ 619,267 | F7: =_xlfn.CONCAT("₱ ",TEXT(ROUND('Analysis & Diagnostics'!B6,2),"###,###")) -> ₱ 362,428
A8: =_xlfn.CONCAT("₱ ",TEXT(ROUND('Analysis & Diagnostics'!F4,2),"###,###")) -> ₱ 19,636 | C8: =_xlfn.CONCAT("₱ ",TEXT(ROUND('Analysis & Diagnostics'!F5,2),"###,###")) -> ₱ 26,403 | F8: =_xlfn.CONCAT("₱ ",TEXT(ROUND('Analysis & Diagnostics'!F6,2),"###,###")) -> ₱ 6,767
A54: General Monthly Trend (Moving Averages)
A119: Income Sources
A147: G-cash Transactions

Sheet Findings
A1: Navigate: | B1: Dashboard | C1: Findings | D1: Pivot & Derived Tables | E1: Analysis & Diagnosis | F1: Data Visualization | G1: Cleaned Data Source | H1: Raw Data Source
A2: 1. Negative Expenses Growth Rate
A20: 2. Income and Net Income Have Negative Growth Rate
A36: Sum of amount | B36: Column Labels
A37: Row Labels | B37: Income
A38: 2024 | B38: 164441
A39: 1 | B39: 25466
A40: salary | B40: 25466
A41: 10 | B41: 27502
A42: ??? | B42: 1021
A43: salary | B43: 26481
A44: 11 | B44: 59992
A45: cash gift | B45: 5000
A46: salary | B46: 27992
A47: year-end bonus | B47: 27000
A48: 12 | B48: 51481
A49: 13th month pay | B49: 25000
A50: salary | B50: 26481
A51: 2025 | B51: 26403
A52: 1 | B52: 26403
A53: salary | B53: 26403
A54: Grand Total | B54: 190844
A59: 3. December 2023 has the highest expenses in record
A108: 4. "Supa" in G-cash has the highest expenses and mostly needed an attention to mind spending.
A160: 5. "Supa" in G-cash expenses affects the general expenses behavior.
A219: 6. "Supa" expenses behaves like creeping expenses.
A274: 7. ₱125 "Supa" is most likely type of "Supa" to be purchased
A309: 8. The trend of "Supa" monthly expenses in G-cash is decreasing.
A329: 9. November 2023 have the highest income because of unlabeled income source.
A366: 10. Because of extra income (cash gift, year-end salary, etc.), months of November mostly have the highest income each year

Sheet Pivot & derived tables
A1: Navigate: | B1: Dashboard | C1: Findings | D1: Pivot & Derived Tables | E1: Analysis & Diagnosis | F1: Data Visualization | G1: Cleaned Data Source | H1: Raw Data Source
A2: Monthly Expenses and Income | H2: Monthly Expenses, Income, and Net Income | N2: Stat Summary of Monthly Expenses, Income, and Net Income | X2: Tables for Data Visualization Crafting Section
A3: Sum of amount | B3: Column Labels | H3: month_year | I3: Expenses | J3: Income | K3: Net Income | L3: Income Growth Rate | N3: stat | O3: Expenses | P3: Income | Q3: Net Income
A4: Row Labels | B4: Expenses | C4: Income | H4: 45231 | I4: 10181 | J4: 70026 | K4: =expen_income_netincome[[#This Row],[Income]] - expen_income_netincome[[#This Row],[Expenses]] -> 59845 | L4: =IFERROR(ROUND((expen_income_netincome[[#This Row],[Income]] - J3) /J3 * 100, 2), 0) -> 0 | N4: skew | O4: =ROUND(SKEW(expen_income_netincome[Expenses]), 3) -> 0.719 | P4: =ROUND(SKEW(expen_income_netincome[Income]), 3) -> 0.926 | Q4: =ROUND(SKEW(expen_income_netincome[Net Income]), 3) -> 0.962
A5: 2023 | B5: 42204 | C5: 156811 | H5: 45261 | I5: 32023 | J5: 43465 | K5: =expen_income_netincome[[#This Row],[Income]] - expen_income_netincome[[#This Row],[Expenses]] -> 11442 | L5: =IFERROR(ROUND((expen_income_netincome[[#This Row],[Income]] - J4) /J4 * 100, 2), 0) -> -37.93 | N5: kurtosis | O5: =ROUND(KURT(expen_income_netincome[Expenses]), 3) -> 0.263 | P5: =ROUND(KURT(expen_income_netincome[Income]), 3) -> -0.141 | Q5: =ROUND(KURT(expen_income_netincome[Net Income]), 3) -> -0.084 | X5: Monthly Expenses and Income | AB5: Sum of Income Details | AF5: Moving Averages of Expenses, Income, and Net Income
A6: Sep | C6: 17732 | H6: 45292 | I6: 9647 | J6: 25466 | K6: =expen_income_netincome[[#This Row],[Income]] - expen_income_netincome[[#This Row],[Expenses]] -> 15819 | L6: =IFERROR(ROUND((expen_income_netincome[[#This Row],[Income]] - J5) /J5 * 100, 2), 0) -> -41.41 | N6: mean | O6: =ROUND(AVERAGE(expen_income_netincome[Expenses]), 2) -> 17122.6 | P6: =ROUND(AVERAGE(expen_income_netincome[Income]), 2) -> 38396.47 | Q6: =ROUND(AVERAGE(expen_income_netincome[Net Income]), 2) -> 21273.87 | X6: Sum of amount | Y6: Column Labels | AB6: Gcash Transactions | AC6: Sum | AD6: Count | AF6: month | AG6: expenses | AH6: expenses_mov_ave | AI6: income | AJ6: income_mov_ave | AK6: net income | AL6: net_income_mov_ave
A7: Oct | C7: 25588 | H7: 45323 | I7: 17583 | J7: 25195 | K7: =expen_income_netincome[[#This Row],[Income]] - expen_income_netincome[[#This Row],[Expenses]] -> 7612 | L7: =IFERROR(ROUND((expen_income_netincome[[#This Row],[Income]] - J6) /J6 * 100, 2), 0) -> -1.06 | N7: stdev | O7: =ROUND(_xlfn.STDEV.S(expen_income_netincome[Expenses]), 2) -> 6503.81 | P7: =ROUND(_xlfn.STDEV.S(expen_income_netincome[Income]), 2) -> 14463.22 | Q7: =ROUND(_xlfn.STDEV.S(expen_income_netincome[Net Income]), 2) -> 17890.35 | X7: Row Labels | Y7: Expenses | Z7: Income | AB7: ??? | AC7: 1021 | AD7: 1 | AF7: ='Pivot & derived tables'!H6 -> 45292 | AG7: 9647 | AH7: =ROUND(AVERAGE('Pivot & derived tables'!I4:I6), 2) -> 17283.67 | AI7: 25466 | AJ7: =ROUND(AVERAGE('Pivot & derived tables'!J4:J6), 2) -> 46319 | AK7: =J6 - I6 -> 15819 | AL7: =ROUND(AVERAGE('Pivot & derived tables'!K4:K6), 2) -> 29035.33
A8: Nov | B8: 10181 | C8: 70026 | H8: 45352 | I8: 18789 | J8: 25195 | K8: =expen_income_netincome[[#This Row],[Income]] - expen_income_netincome[[#This Row],[Expenses]] -> 6406 | L8: =IFERROR(ROUND((expen_income_netincome[[#This Row],[Income]] - J7) /J7 * 100, 2), 0) -> 0 | N8: median | O8: =MEDIAN(expen_income_netincome[Expenses]) -> 17583 | P8: =MEDIAN(expen_income_netincome[Income]) -> 32231 | Q8: =MEDIAN(expen_income_netincome[Net Income]) -> 15819 | X8: 2023 | AB8: 13th month pay | AC8: 25000 | AD8: 1 | AF8: ='Pivot & derived tables'!H7 -> 45323 | AG8: 17583 | AH8: =ROUND(AVERAGE('Pivot & derived tables'!I5:I7), 2) -> 19751 | AI8: 25195 | AJ8: =ROUND(AVERAGE('Pivot & derived tables'!J5:J7), 2) -> 31375.33 | AK8: =J7 - I7 -> 7612 | AL8: =ROUND(AVERAGE('Pivot & derived tables'!K5:K7), 2) -> 11624.33
A9: Dec | B9: 32023 | C9: 43465 | H9: 45383 | I9: 16059 | J9: 32231 | K9: =expen_income_netincome[[#This Row],[Income]] - expen_income_netincome[[#This Row],[Expenses]] -> 16172 | L9: =IFERROR(ROUND((expen_income_netincome[[#This Row],[Income]] - J8) /J8 * 100, 2), 0) -> 27.93 | N9: mad | O9: {=ROUND(SUM(ABS(expen_income_netincome[Expenses] - O8)) / COUNT(expen_income_netincome[Expenses]), 2)} -> 5193.47 | P9: {=ROUND(SUM(ABS(expen_income_netincome[Income] - P8)) / COUNT(expen_income_netincome[Income]), 2)} -> 11545.07 | Q9: {=ROUND(SUM(ABS(expen_income_netincome[Net Income] - Q8)) / COUNT(expen_income_netincome[Net Income]), 2)} -> 13871.8 | X9: Sep | Z9: 17732 | AB9: Bonus salary | AC9: 27000 | AD9: 1 | AF9: ='Pivot & derived tables'!H8 -> 45352 | AG9: 18789 | AH9: =ROUND(AVERAGE('Pivot & derived tables'!I6:I8), 2) -> 15339.67 | AI9: 25195 | AJ9: =ROUND(AVERAGE('Pivot & derived tables'!J6:J8), 2) -> 25285.33 | AK9: =J8 - I8 -> 6406 | AL9: =ROUND(AVERAGE('Pivot & derived tables'!K6:K8), 2) -> 9945.67
A10: 2024 | B10: 194999 | C10: 436053 | H10: 45413 | I10: 12242 | J10: 52230 | K10: =expen_income_netincome[[#This Row],[Income]] - expen_income_netincome[[#This Row],[Expenses]] -> 39988 | L10: =IFERROR(ROUND((expen_income_netincome[[#This Row],[Income]] - J9) /J9 * 100, 2), 0) -> 62.05 | N10: 0.25 | O10: =_xlfn.PERCENTILE.EXC(expen_income_netincome[Expenses], 0.25) -> 11107 | P10: =_xlfn.PERCENTILE.EXC(expen_income_netincome[Income], 0.25) -> 25466 | Q10: =_xlfn.PERCENTILE.EXC(expen_income_netincome[Net Income], 0.25) -> 6767 | X10: Oct | Z10: 25588 | AB10: cash allowance | AC10: 5000 | AD10: 1 | AF10: ='Pivot & derived tables'!H9 -> 45383 | AG10: 16059 | AH10: =ROUND(AVERAGE('Pivot & derived tables'!I7:I9), 2) -> 17477 | AI10: 32231 | AJ10: =ROUND(AVERAGE('Pivot & derived tables'!J7:J9), 2) -> 27540.33 | AK10: =J9 - I9 -> 16172 | AL10: =ROUND(AVERAGE('Pivot & derived tables'!K7:K9), 2) -> 10063.33
A11: Jan | B11: 9647 | C11: 25466 | H11: 45444 | I11: 20411 | J11: 25231 | K11: =expen_income_netincome[[#This Row],[Income]] - expen_income_netincome[[#This Row],[Expenses]] -> 4820 | L11: =IFERROR(ROUND((expen_income_netincome[[#This Row],[Income]] - J10) /J10 * 100, 2), 0) -> -51.69 | N11: 0.75 | O11: =_xlfn.PERCENTILE.INC(expen_income_netincome[Expenses], 0.75) -> 20455 | P11: =_xlfn.PERCENTILE.INC(expen_income_netincome[Income], 0.75) -> 47473 | Q11: =_xlfn.PERCENTILE.INC(expen_income_netincome[Net Income], 0.75) -> 31253.5 | X11: Nov | Y11: 10181 | Z11: 70026 | AB11: cash gift | AC11: 5000 | AD11: 1 | AF11: ='Pivot & derived tables'!H10 -> 45413 | AG11: 12242 | AH11: =ROUND(AVERAGE('Pivot & derived tables'!I8:I10), 2) -> 15696.67 | AI11: 52230 | AJ11: =ROUND(AVERAGE('Pivot & derived tables'!J8:J10), 2) -> 36552 | AK11: =J10 - I10 -> 39988 | AL11: =ROUND(AVERAGE('Pivot & derived tables'!K8:K10), 2) -> 20855.33
A12: Feb | B12: 17583 | C12: 25195 | H12: 45474 | I12: 21985 | J12: 30278 | K12: =expen_income_netincome[[#This Row],[Income]] - expen_income_netincome[[#This Row],[Expenses]] -> 8293 | L12: =IFERROR(ROUND((expen_income_netincome[[#This Row],[Income]] - J11) /J11 * 100, 2), 0) -> 20 | X12: Dec | Y12: 32023 | Z12: 43465 | AB12: chalk allowance | AC12: 5000 | AD12: 1 | AF12: ='Pivot & derived tables'!H11 -> 45444 | AG12: 20411 | AH12: =ROUND(AVERAGE('Pivot & derived tables'!I9:I11), 2) -> 16237.33 | AI12: 25231 | AJ12: =ROUND(AVERAGE('Pivot & derived tables'!J9:J11), 2) -> 36564 | AK12: =J11 - I11 -> 4820 | AL12: =ROUND(AVERAGE('Pivot & derived tables'!K9:K11), 2) -> 20326.67
A13: Mar | B13: 18789 | C13: 25195 | H13: 45505 | I13: 11107 | J13: 42632 | K13: =expen_income_netincome[[#This Row],[Income]] - expen_income_netincome[[#This Row],[Expenses]] -> 31525 | L13: =IFERROR(ROUND((expen_income_netincome[[#This Row],[Income]] - J12) /J12 * 100, 2), 0) -> 40.8 | X13: 2024 | AB13: clothing allowance | AC13: 6000 | AD13: 1 | AF13: ='Pivot & derived tables'!H12 -> 45474 | AG13: 21985 | AH13: =ROUND(AVERAGE('Pivot & derived tables'!I10:I12), 2) -> 18212.67 | AI13: 30278 | AJ13: =ROUND(AVERAGE('Pivot & derived tables'!J10:J12), 2) -> 35913 | AK13: =J12 - I12 -> 8293 | AL13: =ROUND(AVERAGE('Pivot & derived tables'!K10:K12), 2) -> 17700.33
A14: Apr | B14: 16059 | C14: 32231 | H14: 45536 | I14: 11720 | J14: 38620 | K14: =expen_income_netincome[[#This Row],[Income]] - expen_income_netincome[[#This Row],[Expenses]] -> 26900 | L14: =IFERROR(ROUND((expen_income_netincome[[#This Row],[Income]] - J13) /J13 * 100, 2), 0) -> -9.41 | P14: Sum of Income Details | X14: Jan | Y14: 9647 | Z14: 25466 | AB14: Income (with bonus?) | AC14: 44732 | AD14: 1 | AF14: ='Pivot & derived tables'!H13 -> 45505 | AG14: 11107 | AH14: =ROUND(AVERAGE('Pivot & derived tables'!I11:I13), 2) -> 17834.33 | AI14: 42632 | AJ14: =ROUND(AVERAGE('Pivot & derived tables'!J11:J13), 2) -> 32713.67 | AK14: =J13 - I13 -> 31525 | AL14: =ROUND(AVERAGE('Pivot & derived tables'!K11:K13), 2) -> 14879.33
A15: May | B15: 12242 | C15: 52230 | H15: 45566 | I15: 25236 | J15: 27502 | K15: =expen_income_netincome[[#This Row],[Income]] - expen_income_netincome[[#This Row],[Expenses]] -> 2266 | L15: =IFERROR(ROUND((expen_income_netincome[[#This Row],[Income]] - J14) /J14 * 100, 2), 0) -> -28.79 | Q15: Column Labels | X15: Feb | Y15: 17583 | Z15: 25195 | AB15: PBB | AC15: 12400 | AD15: 1 | AF15: ='Pivot & derived tables'!H14 -> 45536 | AG15: 11720 | AH15: =ROUND(AVERAGE('Pivot & derived tables'!I12:I14), 2) -> 14937.33 | AI15: 38620 | AJ15: =ROUND(AVERAGE('Pivot & derived tables'!J12:J14), 2) -> 37176.67 | AK15: =J14 - I14 -> 26900 | AL15: =ROUND(AVERAGE('Pivot & derived tables'!K12:K14), 2) -> 22239.33
A16: Jun | B16: 20411 | C16: 25231 | H16: 45597 | I16: 9721 | J16: 59992 | K16: =expen_income_netincome[[#This Row],[Income]] - expen_income_netincome[[#This Row],[Expenses]] -> 50271 | L16: =IFERROR(ROUND((expen_income_netincome[[#This Row],[Income]] - J15) /J15 * 100, 2), 0) -> 118.14 | Q16: Income | X16: Mar | Y16: 18789 | Z16: 25195 | AB16: salary | AC16: 430554 | AD16: 32 | AF16: ='Pivot & derived tables'!H15 -> 45566 | AG16: 25236 | AH16: =ROUND(AVERAGE('Pivot & derived tables'!I13:I15), 2) -> 16021 | AI16: 27502 | AJ16: =ROUND(AVERAGE('Pivot & derived tables'!J13:J15), 2) -> 36251.33 | AK16: =J15 - I15 -> 2266 | AL16: =ROUND(AVERAGE('Pivot & derived tables'!K13:K15), 2) -> 20230.33
A17: Jul | B17: 21985 | C17: 30278 | H17: 45627 | I17: 20499 | J17: 51481 | K17: =expen_income_netincome[[#This Row],[Income]] - expen_income_netincome[[#This Row],[Expenses]] -> 30982 | L17: =IFERROR(ROUND((expen_income_netincome[[#This Row],[Income]] - J16) /J16 * 100, 2), 0) -> -14.19 | P17: Row Labels | Q17: Sum | R17: Count | S17: Percentage of Sum | X17: Apr | Y17: 16059 | Z17: 32231 | AB17: SRI | AC17: 18000 | AD17: 1 | AF17: ='Pivot & derived tables'!H16 -> 45597 | AG17: 9721 | AH17: =ROUND(AVERAGE('Pivot & derived tables'!I14:I16), 2) -> 15559 | AI17: 59992 | AJ17: =ROUND(AVERAGE('Pivot & derived tables'!J14:J16), 2) -> 42038 | AK17: =J16 - I16 -> 50271 | AL17: =ROUND(AVERAGE('Pivot & derived tables'!K14:K16), 2) -> 26479
A18: Aug | B18: 11107 | C18: 42632 | H18: 45658 | I18: 19636 | J18: 26403 | K18: =expen_income_netincome[[#This Row],[Income]] - expen_income_netincome[[#This Row],[Expenses]] -> 6767 | L18: =IFERROR(ROUND((expen_income_netincome[[#This Row],[Income]] - J17) /J17 * 100, 2), 0) -> -48.71 | P18: ??? | Q18: 1021 | R18: 1 | S18: 0.0016487234 | X18: May | Y18: 12242 | Z18: 52230 | AB18: Tahong harvest | AC18: 12560 | AD18: 1 | AF18: ='Pivot & derived tables'!H17 -> 45627 | AG18: 20499 | AH18: =ROUND(AVERAGE('Pivot & derived tables'!I15:I17), 2) -> 18485.33 | AI18: 51481 | AJ18: =ROUND(AVERAGE('Pivot & derived tables'!J15:J17), 2) -> 46325 | AK18: =J17 - I17 -> 30982 | AL18: =ROUND(AVERAGE('Pivot & derived tables'!K15:K17), 2) -> 27839.67
A19: Sep | B19: 11720 | C19: 38620 | P19: 13th month pay | Q19: 25000 | R19: 1 | S19: 0.040370309 | X19: Jun | Y19: 20411 | Z19: 25231 | AB19: year-end bonus | AC19: 27000 | AD19: 1 | AF19: ='Pivot & derived tables'!H18 -> 45658 | AG19: 19636 | AH19: =ROUND(AVERAGE('Pivot & derived tables'!I16:I18), 2) -> 16618.67 | AI19: 26403 | AJ19: =ROUND(AVERAGE('Pivot & derived tables'!J16:J18), 2) -> 45958.67 | AK19: =J18 - I18 -> 6767 | AL19: =ROUND(AVERAGE('Pivot & derived tables'!K16:K18), 2) -> 29340
A20: Oct | B20: 25236 | C20: 27502 | P20: Bonus salary | Q20: 27000 | R20: 1 | S20: 0.043599933 | X20: Jul | Y20: 21985 | Z20: 30278
A21: Nov | B21: 9721 | C21: 59992 | P21: cash allowance | Q21: 5000 | R21: 1 | S21: 0.0080740618 | X21: Aug | Y21: 11107 | Z21: 42632
A22: Dec | B22: 20499 | C22: 51481 | H22: Expenses and Income Average, Stdev, Sum, and Counts | P22: cash gift | Q22: 5000 | R22: 1 | S22: 0.0080740618 | X22: Sep | Y22: 11720 | Z22: 38620
A23: 2025 | B23: 19636 | C23: 26403 | I23: Row Labels | J23: Average | K23: StdDev | L23: Sum | M23: Count | P23: chalk allowance | Q23: 5000 | R23: 1 | S23: 0.0080740618 | X23: Oct | Y23: 25236 | Z23: 27502
A24: Jan | B24: 19636 | C24: 26403 | I24: Expenses | J24: 439.79281 | K24: 1081.4702 | L24: 256839 | M24: 584 | P24: clothing allowance | Q24: 6000 | R24: 1 | S24: 0.0096888741 | X24: Nov | Y24: 9721 | Z24: 59992
A25: Grand Total | B25: 256839 | C25: 619267 | I25: Income | J25: 14074.25 | K25: 6963.4262 | L25: 619267 | M25: 44 | P25: Income (with bonus?) | Q25: 44732 | R25: 1 | S25: 0.072233786 | X25: Dec | Y25: 20499 | Z25: 51481
P26: PBB | Q26: 12400 | R26: 1 | S26: 0.020023673 | X26: 2025
P27: salary | Q27: 430554 | R27: 32 | S27: 0.69526392 | X27: Jan | Y27: 19636 | Z27: 26403
A28: Total Expenses or Income in Every Transaction Detail | P28: SRI | Q28: 18000 | R28: 1 | S28: 0.029066622 | X28: Grand Total | Y28: 256839 | Z28: 619267
A29: Sum of amount | B29: Column Labels | P29: Tahong harvest | Q29: 12560 | R29: 1 | S29: 0.020282043
A30: Row Labels | B30: Expenses | C30: Income | P30: year-end bonus | Q30: 27000 | R30: 1 | S30: 0.043599933
A31: ??? | C31: 1021 | P31: Grand Total | Q31: 619267 | R31: 44 | S31: 1 | X31: G-cash Total Expenses
A32: 13th month pay | C32: 25000 | X32: details | Y32: amount | Z32: count | AA32: average | AB32: percentage
A33: aficionado (F28) | B33: 640 | H33: G-cash Total Expenses | M33: Daily Total Supa Expenses | X33: bag | Y33: 1000 | Z33: 1 | AA33: 1000 | AB33: =ROUND(Table23[[#This Row],[amount]] / SUM(Table23[amount]) * 100, 2) -> 3.92
A34: aragmot | B34: 3340 | I34: Column Labels | M34: Sum of amount | N34: Column Labels | P34: Statistic Summary | X34: donation | Y34: 125 | Z34: 1 | AA34: 125 | AB34: =ROUND(Table23[[#This Row],[amount]] / SUM(Table23[amount]) * 100, 2) -> 0.49
A35: Arot | B35: 95 | I35: G-cash | N35: Supa | P35: stat | Q35: Expenses | T35: Daily Total Supa Expenses | X35: Genshin Welkin | Y35: 1960 | Z35: 7 | AA35: 280 | AB35: =ROUND(Table23[[#This Row],[amount]] / SUM(Table23[amount]) * 100, 2) -> 7.69
A36: asite | B36: 300 | P36: skew | Q36: =ROUND(SKEW($N$38:$N$86), 3) -> 0.053 | T36: date | U36: supa_expenses | X36: Membership gift | Y36: 258 | Z36: 2 | AA36: 129 | AB36: =ROUND(Table23[[#This Row],[amount]] / SUM(Table23[amount]) * 100, 2) -> 1.01
A37: asiti | B37: 210 | H37: Row Labels | I37: Sum of amount | J37: Count of amount2 | K37: Average of amount2 | M37: Row Labels | P37: kurtosis | Q37: =ROUND(KURT($N$38:$N$86), 3) -> 0.585 | T37: 45243 | U37: 150 | X37: mobile load (magic data) | Y37: 399 | Z37: 1 | AA37: 399 | AB37: =ROUND(Table23[[#This Row],[amount]] / SUM(Table23[amount]) * 100, 2) -> 1.56
A38: bado | B38: 1050 | H38: bag | I38: 1000 | J38: 1 | K38: 1000 | M38: 45243 | N38: 150 | P38: mean | Q38: =ROUND(AVERAGE($N$38:$N$86), 2) -> 125.59 | T38: 45245 | U38: 125 | X38: Palaman peanut | Y38: 500 | Z38: 1 | AA38: 500 | AB38: =ROUND(Table23[[#This Row],[amount]] / SUM(Table23[amount]) * 100, 2) -> 1.96
A39: bag | B39: 1000 | H39: donation | I39: 125 | J39: 1 | K39: 125 | M39: 45245 | N39: 125 | P39: stdev | Q39: =ROUND(_xlfn.STDEV.S($N$38:$N$86), 2) -> 48.81 | T39: 45253 | U39: 125 | X39: sheena-related | Y39: 150 | Z39: 1 | AA39: 150 | AB39: =ROUND(Table23[[#This Row],[amount]] / SUM(Table23[amount]) * 100, 2) -> 0.59
A40: bag sena | B40: 1099 | H40: Genshin Welkin | I40: 1960 | J40: 7 | K40: 280 | M40: 45253 | N40: 125 | P40: median | Q40: =MEDIAN($N$38:$N$86) -> 125 | T40: 45262 | U40: 125 | X40: Spotify | Y40: 2823 | Z40: 12 | AA40: 235.25 | AB40: =ROUND(Table23[[#This Row],[amount]] / SUM(Table23[amount]) * 100, 2) -> 11.07
A41: balay | B41: 73000 | H41: Membership gift | I41: 258 | J41: 2 | K41: 129 | M41: 45262 | N41: 125 | P41: mad | Q41: {=ROUND(SUM(ABS($N$38:$N$86 - Q40)) / COUNT($N$38:$N$86), 2)} -> 30.18 | T41: 45268 | U41: 125 | X41: steam | Y41: 1705 | Z41: 7 | AA41: 243.57 | AB41: =ROUND(Table23[[#This Row],[amount]] / SUM(Table23[amount]) * 100, 2) -> 6.69
A42: ballpen | B42: 12 | H42: mobile load (magic data) | I42: 399 | J42: 1 | K42: 399 | M42: 45268 | N42: 125 | P42: 0.25 | Q42: =_xlfn.PERCENTILE.EXC($N$38:$N$86, 0.25) -> 125 | T42: 45298 | U42: 175 | X42: Supa | Y42: 6154 | Z42: 66 | AA42: 93.24 | AB42: =ROUND(Table23[[#This Row],[amount]] / SUM(Table23[amount]) * 100, 2) -> 24.13
A43: bank withdraw fee | B43: 372 | H43: Palaman peanut | I43: 500 | J43: 1 | K43: 500 | M43: 45298 | N43: 175 | P43: 0.75 | Q43: =_xlfn.PERCENTILE.INC($N$38:$N$86, 0.75) -> 129 | T43: 45299 | U43: 25 | X43: welcome party aragmot | Y43: 650 | Z43: 1 | AA43: 650 | AB43: =ROUND(Table23[[#This Row],[amount]] / SUM(Table23[amount]) * 100, 2) -> 2.55
A44: bata medyas | B44: 69 | H44: sheena-related | I44: 150 | J44: 1 | K44: 150 | M44: 45299 | N44: 25 | T44: 45300 | U44: 50 | X44: wifi load (family access) | Y44: 3981 | Z44: 20 | AA44: 199.05 | AB44: =ROUND(Table23[[#This Row],[amount]] / SUM(Table23[amount]) * 100, 2) -> 15.61
A45: bata pajama w/ hood | B45: 269 | H45: Spotify | I45: 2823 | J45: 12 | K45: 235.25 | M45: 45300 | N45: 50 | T45: 45306 | U45: 125 | X45: wifi load (magic data) | Y45: 4494 | Z45: 7 | AA45: 642 | AB45: =ROUND(Table23[[#This Row],[amount]] / SUM(Table23[amount]) * 100, 2) -> 17.62
A46: battery | B46: 3600 | H46: steam | I46: 1705 | J46: 7 | K46: 243.57143 | M46: 45306 | N46: 125 | T46: 45309 | U46: 125 | X46: YT Membership | Y46: 1290 | Z46: 10 | AA46: 129 | AB46: =ROUND(Table23[[#This Row],[amount]] / SUM(Table23[amount]) * 100, 2) -> 5.06
A47: bayad absent | B47: 500 | H47: Supa | I47: 6154 | J47: 66 | K47: 93.242424 | M47: 45309 | N47: 125 | T47: 45310 | U47: 125 | X47: YT sticker | Y47: 15 | Z47: 1 | AA47: 15 | AB47: =ROUND(Table23[[#This Row],[amount]] / SUM(Table23[amount]) * 100, 2) -> 0.06
A48: Bayad referee | B48: 300 | H48: welcome party aragmot | I48: 650 | J48: 1 | K48: 650 | M48: 45310 | N48: 125 | T48: 45311 | U48: 125
A49: beer (1 case) | B49: 720 | H49: wifi load (family access) | I49: 3981 | J49: 20 | K49: 199.05 | M49: 45311 | N49: 125 | T49: 45312 | U49: 125
A50: Bioderm | B50: 463 | H50: wifi load (magic data) | I50: 4494 | J50: 7 | K50: 642 | M50: 45312 | N50: 125 | T50: 45315 | U50: 150
A51: black shoes | B51: 930 | H51: YT Membership | I51: 1290 | J51: 10 | K51: 129 | M51: 45315 | N51: 150 | T51: 45316 | U51: 125
A52: bluetooth speaker | B52: 1990 | H52: YT sticker | I52: 15 | J52: 1 | K52: 15 | M52: 45316 | N52: 125 | T52: 45322 | U52: 125
A53: bokbok | B53: 150 | H53: Grand Total | I53: 25504 | J53: 138 | K53: 184.81159 | M53: 45322 | N53: 125 | T53: 45323 | U53: 225
A54: bonay | B54: 22 | M54: 45323 | N54: 225 | T54: 45344 | U54: 129
A55: Bonus salary | C55: 27000 | M55: 45344 | N55: 129 | T55: 45353 | U55: 125
A56: boxer shorts | B56: 2234 | M56: 45353 | N56: 125 | T56: 45356 | U56: 175
A57: bronze nail | B57: 550 | H57: Daily Expenses | M57: 45356 | N57: 175 | T57: 45384 | U57: 50
A58: brownies | B58: 175 | H58: Sum of amount | I58: Column Labels | M58: 45384 | N58: 50 | T58: 45387 | U58: 125
A59: brutsa | B59: 50 | H59: Row Labels | I59: Expenses | M59: 45387 | N59: 125 | T59: 45398 | U59: 125
A60: burger | B60: 87 | H60: 45235 | I60: 8636 | M60: 45398 | N60: 125 | T60: 45415 | U60: 175
A61: burger steak | B61: 20 | H61: 45236 | I61: 214 | M61: 45415 | N61: 175 | T61: 45418 | U61: 175
A62: cash allowance | C62: 5000 | H62: 45240 | I62: 73 | M62: 45418 | N62: 175 | T62: 45430 | U62: 50
A63: cash gift | C63: 5000 | H63: 45243 | I63: 162 | M63: 45430 | N63: 50 | T63: 45440 | U63: 125
A64: cellophane | B64: 30 | H64: 45244 | I64: 25 | M64: 45440 | N64: 125 | T64: 45447 | U64: 125
A65: Century Tuna | B65: 43 | H65: 45245 | I65: 125 | M65: 45447 | N65: 125 | T65: 45449 | U65: 125
A66: chalk | B66: 60 | H66: 45246 | I66: 55 | M66: 45449 | N66: 125 | T66: 45450 | U66: 200
A67: chalk allowance | C67: 5000 | H67: 45247 | I67: 37 | M67: 45450 | N67: 200 | T67: 45456 | U67: 125
A68: Choco-choco | B68: 20 | H68: 45248 | I68: 320 | M68: 45456 | N68: 125 | T68: 45457 | U68: 50
A69: clothing allowance | C69: 6000 | H69: 45252 | I69: 409 | M69: 45457 | N69: 50 | T69: 45463 | U69: 50
A70: crispy king paniudto | B70: 77 | H70: 45253 | I70: 125 | M70: 45463 | N70: 50 | T70: 45466 | U70: 225
A71: diatabs | B71: 30 | H71: 45262 | I71: 125 | M71: 45466 | N71: 225 | T71: 45470 | U71: 100
A72: disposable cups | B72: 40 | H72: 45263 | I72: 265 | M72: 45470 | N72: 100 | T72: 45471 | U72: 125
A73: district t-shirt | B73: 600 | H73: 45264 | I73: 1525 | M73: 45471 | N73: 125 | T73: 45483 | U73: 175
A74: donation | B74: 525 | H74: 45266 | I74: 239 | M74: 45483 | N74: 175 | T74: 45485 | U74: 50
A75: Earphone | B75: 180 | H75: 45267 | I75: 25 | M75: 45485 | N75: 50 | T75: 45503 | U75: 250
A76: earpod | B76: 899 | H76: 45268 | I76: 125 | M76: 45503 | N76: 250 | T76: 45519 | U76: 125
A77: Ebo Sweldo | B77: 9200 | H77: 45269 | I77: 268 | M77: 45519 | N77: 125 | T77: 45539 | U77: 125
A78: eco-bag | B78: 90 | H78: 45270 | I78: 7100 | M78: 45539 | N78: 125 | T78: 45540 | U78: 75
A79: epoxy | B79: 1255 | H79: 45271 | I79: 599 | M79: 45540 | N79: 75 | T79: 45547 | U79: 125
A80: extension wire | B80: 135 | H80: 45273 | I80: 70 | M80: 45547 | N80: 125 | T80: 45570 | U80: 175
A81: Family day price | B81: 50 | H81: 45274 | I81: 599 | M81: 45570 | N81: 175 | T81: 45581 | U81: 125
... A85: gaming chair | B85: 2542 | H85: 45281 | I85: 768 | M85: 45589 | N85: 125 | T85: 45590 | U85: 25
A86: Gasolina | B86: 31270 | H86: 45282 | I86: 129 | M86: 45590 | N86: 25
A87: Genshin Welkin | B87: 1960 | H87: 45283 | I87: 4035 | M87: Grand Total | N87: 6154
A88: grocery | B88: 87 | H88: 45284 | I88: 500
A89: halo-halo (4x) | B89: 40 | H89: 45285 | I89: 100
A90: handa (birthday) | B90: 4000 | H90: 45286 | I90: 199
A91: hatag kanda mama | B91: 3000 | H91: 45288 | I91: 5402
A92: HDD enclosure | B92: 599 | H92: 45291 | I92: 160 | L92: Data Searcher (Filtering)
A93: hoody jacket | B93: 263 | H93: 45292 | I93: 200 | M93: Column Labels
A94: hotdog | B94: 75 | H94: 45297 | I94: 239 | M94: Income
A95: ID picture | B95: 245 | H95: 45298 | I95: 209 | L95: Row Labels | M95: Sum of amount | N95: Count of amount | O95: Average of amount
A96: Income (with bonus?) | C96: 44732 | H96: 45299 | I96: 417 | L96: 2023 | M96: 70026 | N96: 3 | O96: 23342
A97: Ink | B97: 1000 | H97: 45300 | I97: 223 | L97: 11 | M97: 70026 | N97: 3 | O97: 23342
A98: inom | B98: 200 | H98: 45303 | I98: 5932 | L98: Income (with bonus?) | M98: 44732 | N98: 1 | O98: 44732
A99: intrams props | B99: 500 | H99: 45305 | I99: 260 | L99: salary | M99: 12734 | N99: 1 | O99: 12734
A100: irimnon | B100: 2990 | H100: 45306 | I100: 425 | L100: Tahong harvest | M100: 12560 | N100: 1 | O100: 12560
A101: Jollibee | B101: 1026 | H101: 45308 | I101: 200 | L101: 2024 | M101: 59992 | N101: 4 | O101: 14998
A102: Kape | B102: 3800 | H102: 45309 | I102: 125 | L102: 11 | M102: 59992 | N102: 4 | O102: 14998
A103: ketchup | B103: 60 | H103: 45310 | I103: 125 | L103: cash gift | M103: 5000 | N103: 1 | O103: 5000
...

Sheet Analysis & Diagnostics
A1: Navigate: | B1: Dashboard | C1: Findings | D1: Pivot & Derived Tables | E1: Analysis & Diagnosis | F1: Data Visualization | G1: Cleaned Data Source | H1: Raw Data Source
A2: Key Performance Indicator
A3: KPI | B3: Total | C3: Monthly Average | D3: Monthly Median | E3: Growth Rate | F3: Latest Month Record | I3: Income scope | J3: Expeneses | K3: Net Income
A4: Expenses | B4: =SUMIF(cleaned_personal_finance_data[transaction], "Expenses", cleaned_personal_finance_data[amount]) -> 256839 | C4: ='Pivot & derived tables'!O6 -> 17122.6 | D4: =MEDIAN('Pivot & derived tables'!Y8:Y27) -> 17583 | E4: =('Pivot & derived tables'!I18 - 'Pivot & derived tables'!I17) / 'Pivot & derived tables'!I17 -> -0.042099615 | F4: ='Pivot & derived tables'!I18 -> 19636 | I4: Latest Month | J4: =ROUND(Table414[[#This Row],[Latest Month Record]]/F5 * 100, 2) -> 74.37 | K4: =ROUND(F6/F5 * 100, 2) -> 25.63
A5: Income | B5: =SUMIF(cleaned_personal_finance_data[transaction], "Income", cleaned_personal_finance_data[amount]) -> 619267 | C5: =AVERAGE('Pivot & derived tables'!Z8:Z27) -> 36427.471 | D5: =MEDIAN('Pivot & derived tables'!Z8:Z27) -> 30278 | E5: =('Pivot & derived tables'!J18 - 'Pivot & derived tables'!J17) / 'Pivot & derived tables'!J17 -> -0.48713117 | F5: ='Pivot & derived tables'!J18 -> 26403 | I5: Full Period Income | J5: =ROUND(B4/Table414[[#This Row],[Total]] * 100, 2) -> 41.47 | K5: =ROUND(B6/Table414[[#This Row],[Total]] * 100, 2) -> 58.53
A6: Net Income | B6: =B5 - B4 -> 362428 | C6: ='Pivot & derived tables'!Q6 -> 21273.87 | D6: ='Pivot & derived tables'!Q8 -> 15819 | E6: =('Pivot & derived tables'!K18 - 'Pivot & derived tables'!K17) / 'Pivot & derived tables'!K17 -> -0.78158285 | F6: ='Pivot & derived tables'!K18 -> 6767
A9: Analysis 1: Why there is a huge decrease in Net Income in the latest month (Jan 2025)?
D11: Sum of amount | E11: Column Labels | H11: Month (in 2025) | I11: Expenses | J11: Income | K11: Net Income | L11: Net Income Growth %
D12: Row Labels | E12: Income | H12: Oct. 2024 | I12: 25236 | J12: 27502 | K12: =Table17[[#This Row],[Income]] - Table17[[#This Row],[Expenses]] -> 2266 | L12: =IFERROR(ROUND((Table17[[#This Row],[Net Income]] - K11) / K11 * 100, 2), "")
D13: 2024 | E13: 164441 | H13: Nov. 2024 | I13: 9721 | J13: 59992 | K13: =Table17[[#This Row],[Income]] - Table17[[#This Row],[Expenses]] -> 50271 | L13: =IFERROR(ROUND((Table17[[#This Row],[Net Income]] - K12) / K12 * 100, 2), "") -> 2118.49
D14: 1 | E14: 25466 | H14: Dec. 2024 | I14: 20499 | J14: 51481 | K14: =Table17[[#This Row],[Income]] - Table17[[#This Row],[Expenses]] -> 30982 | L14: =IFERROR(ROUND((Table17[[#This Row],[Net Income]] - K13) / K13 * 100, 2), "") -> -38.37
D15: salary | E15: 25466 | H15: Jan. 2025 | I15: 19636 | J15: 26403 | K15: =Table17[[#This Row],[Income]] - Table17[[#This Row],[Expenses]] -> 6767 | L15: =IFERROR(ROUND((Table17[[#This Row],[Net Income]] - K14) / K14 * 100, 2), "") -> -78.16
D16: 10 | E16: 27502
D17: ??? | E17: 1021
D18: salary | E18: 26481
D19: 11 | E19: 59992
D20: cash gift | E20: 5000
D21: salary | E21: 27992
D22: year-end bonus | E22: 27000
D23: 12 | E23: 51481
D24: 13th month pay | E24: 25000
D25: salary | E25: 26481
D26: 2025 | E26: 26403
D27: 1 | E27: 26403
D28: salary | E28: 26403
D29: Grand Total | E29: 190844
A58: Analysis 2: What is the reason why December 2023 has the highest expenses in record?
A71: December 2023 Expenses | F71: December 2023 Expenses
B72: Column Labels | F72: transaction_detail | G72: expenses | H72: expense_prcnt | I72: count | J72: category
B73: Expenses | F73: balay | G73: 5000 | H73: 0.15613778 | I73: 1 | J73: bills
A74: Row Labels | B74: Sum | C74: Sum (%) | D74: Count | F74: battery | G74: 3600 | H74: 0.1124192 | I74: 1 | J74: laptop-related
A75: 2023 | B75: 32023 | C75: 1 | D75: 67 | F75: hatag kanda mama | G75: 3000 | H75: 0.093682666 | I75: 1 | J75: bills
A76: 12 | B76: 32023 | C76: 1 | D76: 67 | F76: SSD | G76: 2900 | H76: 0.09055991 | I76: 1 | J76: laptop-related
A77: balay | B77: 5000 | C77: 0.15613778 | D77: 1 | F77: laptop keyboard | G77: 2600 | H77: 0.081191644 | I77: 1 | J77: laptop-related
A78: battery | B78: 3600 | C78: 0.1124192 | D78: 1 | F78: Gasolina | G78: 2100 | H78: 0.065577866 | I78: 1 | J78: bills
A79: hatag kanda mama | B79: 3000 | C79: 0.093682666 | D79: 1 | F79: Ebo Sweldo | G79: 1500 | H79: 0.046841333 | I79: 1 | J79: bills
A80: SSD | B80: 2900 | C80: 0.09055991 | D80: 1 | F80: laptop upgrade labor | G80: 1500 | H80: 0.046841333 | I80: 1 | J80: laptop-related
A81: laptop keyboard | B81: 2600 | C81: 0.081191644 | D81: 1 | F81: medisina | G81: 1375 | H81: 0.042937888 | I81: 1 | J81: medicine
A82: Gasolina | B82: 2100 | C82: 0.065577866 | D82: 1 | F82: Pamasahe | G82: 1120 | H82: 0.034974862 | I82: 15 | J82: transportation
A83: Ebo Sweldo | B83: 1500 | C83: 0.046841333 | D83: 1 | F83: steam | G83: 768 | H83: 0.023982762 | I83: 1 | J83: entertainment
A84: laptop upgrade labor | B84: 1500 | C84: 0.046841333 | D84: 1 | F84: district t-shirt | G84: 600 | H84: 0.018736533 | I84: 1 | J84: job-related
A85: medisina | B85: 1375 | C85: 0.042937888 | D85: 1 | F85: HDD enclosure | G85: 599 | H85: 0.018705306 | I85: 1 | J85: laptop-related
A86: Pamasahe | B86: 1120 | C86: 0.034974862 | D86: 15 | F86: wifi load (magic data) | G86: 599 | H86: 0.018705306 | I86: 1 | J86: personal necessity
A87: steam | B87: 768 | C87: 0.023982762 | D87: 1 | F87: aragmot | G87: 544 | H87: 0.01698779 | I87: 1 | J87: job-related
A88: district t-shirt | B88: 600 | C88: 0.018736533 | D88: 1 | F88: keyboard labor | G88: 500 | H88: 0.015613778 | I88: 1 | J88: laptop-related
... A114: tinapay | B114: 20 | C114: 0.0006245511 | D114: 1 | F114: pandesal | G114: 10 | H114: 0.00031227555 | I114: 1 | J114: food
A115: putok | B115: 20 | C115: 0.0006245511 | D115: 1
A116: Noodles beef | B116: 13 | C116: 0.00040595822 | D116: 1
A117: fita | B117: 10 | C117: 0.00031227555 | D117: 1
A118: pandesal | B118: 10 | C118: 0.00031227555 | D118: 1
A119: Grand Total | B119: 32023 | C119: 1 | D119: 67 | G119: December 2023 Expenses by Category
G120: category | H120: expense | I120: expense_propxn | J120: expense_prcnt | K120: count | L120: average_rounded
G121: laptop-related | H121: 11699 | I121: 0.36533117 | J121: =ROUND(Table22[[#This Row],[expense_propxn]] * 100, 2) -> 36.53 | K121: 6 | L121: =ROUND(Table22[[#This Row],[expense]]/Table22[[#This Row],[count]], 2) -> 1949.83
A122: December 2023 Expenses by Category | G122: bills | H122: 11600 | I122: 0.36223964 | J122: =ROUND(Table22[[#This Row],[expense_propxn]] * 100, 2) -> 36.22 | K122: 4 | L122: =ROUND(Table22[[#This Row],[expense]]/Table22[[#This Row],[count]], 2) -> 2900
A123: Row Labels | B123: Sum of expenses | C123: Sum of expense_prcnt | D123: Sum of count | G123: entertainment | H123: 2166 | I123: 0.067638885 | J123: =ROUND(Table22[[#This Row],[expense_propxn]] * 100, 2) -> 6.76 | K123: 8 | L123: =ROUND(Table22[[#This Row],[expense]]/Table22[[#This Row],[count]], 2) -> 270.75
A124: laptop-related | B124: 11699 | C124: 0.36533117 | D124: 6 | G124: food | H124: 1747 | I124: 0.054554539 | J124: =ROUND(Table22[[#This Row],[expense_propxn]] * 100, 2) -> 5.46 | K124: 23 | L124: =ROUND(Table22[[#This Row],[expense]]/Table22[[#This Row],[count]], 2) -> 75.96
A125: bills | B125: 11600 | C125: 0.36223964 | D125: 4 | G125: medicine | H125: 1375 | I125: 0.042937888 | J125: =ROUND(Table22[[#This Row],[expense_propxn]] * 100, 2) -> 4.29 | K125: 1 | L125: =ROUND(Table22[[#This Row],[expense]]/Table22[[#This Row],[count]], 2) -> 1375
A126: entertainment | B126: 2166 | C126: 0.067638885 | D126: 8 | G126: job-related | H126: 1244 | I126: 0.038847079 | J126: =ROUND(Table22[[#This Row],[expense_propxn]] * 100, 2) -> 3.88 | K126: 4 | L126: =ROUND(Table22[[#This Row],[expense]]/Table22[[#This Row],[count]], 2) -> 311
A127: food | B127: 1747 | C127: 0.054554539 | D127: 23 | G127: transportation | H127: 1120 | I127: 0.034974862 | J127: =ROUND(Table22[[#This Row],[expense_propxn]] * 100, 2) -> 3.5 | K127: 15 | L127: =ROUND(Table22[[#This Row],[expense]]/Table22[[#This Row],[count]], 2) -> 74.67
A128: medicine | B128: 1375 | C128: 0.042937888 | D128: 1 | G128: personal necessity | H128: 1072 | I128: 0.033475939 | J128: =ROUND(Table22[[#This Row],[expense_propxn]] * 100, 2) -> 3.35 | K128: 6 | L128: =ROUND(Table22[[#This Row],[expense]]/Table22[[#This Row],[count]], 2) -> 178.67
A129: job-related | B129: 1244 | C129: 0.038847079 | D129: 4
A130: transportation | B130: 1120 | C130: 0.034974862 | D130: 15
A131: personal necessity | B131: 1072 | C131: 0.033475939 | D131: 6
A132: Grand Total | B132: 32023 | C132: 1 | D132: 67
A170: Analysis 3: What transaction in G-cash has the highest expenses and mostly needed an attention to mind spending?
A233: Analysis 4: Is "Supa" in G-cash expenses affecting the general expenses behavior?
A235: Total Expenses of Each Transaction Detail | I235: Top 20 Exepenses | R235: Statistic Summary
B236: Column Labels | I236: Detail | J236: Sum of G-cash Expenses | K236: Count of G-cash | L236: Total Expenses | M236: Total Count | N236: Rank | O236: G-cash Percentage | P236: Total Percentage | R236: statistic | S236: value
B237: Expenses | F237: Total Sum of amount | G237: Total Count of amount2 | I237: balay | L237: 73000 | M237: 14 | N237: 1 | O237: =ROUND(Table20[[#This Row],[Sum of G-cash Expenses]]/Table20[[#This Row],[Total Expenses]] * 100, 2) -> 0 | P237: =ROUND(Table20[[#This Row],[Total Expenses]] / $B$4 * 100, 2) -> 28.42 | R237: Sum | S237: =SUM(Table20[Total Expenses]) -> 193429
B238: G-cash | D238: Stash | I238: Gasolina | L238: 31270 | M238: 15 | N238: 2 | O238: =ROUND(Table20[[#This Row],[Sum of G-cash Expenses]]/Table20[[#This Row],[Total Expenses]] * 100, 2) -> 0 | P238: =ROUND(Table20[[#This Row],[Total Expenses]] / $B$4 * 100, 2) -> 12.17 | R238: Percent from Total Expenses | S238: =ROUND(S237 / B4 * 100, 2) -> 75.31
A239: Row Labels | B239: Sum of amount | C239: Count of amount2 | D239: Sum of amount | E239: Count of amount2 | I239: letson | L239: 10000 | M239: 1 | N239: 3 | O239: =ROUND(Table20[[#This Row],[Sum of G-cash Expenses]]/Table20[[#This Row],[Total Expenses]] * 100, 2) -> 0 | P239: =ROUND(Table20[[#This Row],[Total Expenses]] / $B$4 * 100, 2) -> 3.89
A240: balay | D240: 73000 | E240: 14 | F240: 73000 | G240: 14 | I240: Ebo Sweldo | L240: 9200 | M240: 6 | N240: 4 | O240: =ROUND(Table20[[#This Row],[Sum of G-cash Expenses]]/Table20[[#This Row],[Total Expenses]] * 100, 2) -> 0 | P240: =ROUND(Table20[[#This Row],[Total Expenses]] / $B$4 * 100, 2) -> 3.58
A241: Gasolina | D241: 31270 | E241: 15 | F241: 31270 | G241: 15 | I241: sheena-related | J241: 150 | K241: 1 | L241: 7200 | M241: 4 | N241: 5 | O241: =ROUND(Table20[[#This Row],[Sum of G-cash Expenses]]/Table20[[#This Row],[Total Expenses]] * 100, 2) -> 2.08 | P241: =ROUND(Table20[[#This Row],[Total Expenses]] / $B$4 * 100, 2) -> 2.8
A242: letson | D242: 10000 | E242: 1 | F242: 10000 | G242: 1 | I242: ref (hulog) | L242: 7000 | M242: 1 | N242: 6 | O242: =ROUND(Table20[[#This Row],[Sum of G-cash Expenses]]/Table20[[#This Row],[Total Expenses]] * 100, 2) -> 0 | P242: =ROUND(Table20[[#This Row],[Total Expenses]] / $B$4 * 100, 2) -> 2.73
A243: Ebo Sweldo | D243: 9200 | E243: 6 | F243: 9200 | G243: 6 | I243: Pamasahe | L243: 6587 | M243: 87 | N243: 7 | O243: =ROUND(Table20[[#This Row],[Sum of G-cash Expenses]]/Table20[[#This Row],[Total Expenses]] * 100, 2) -> 0 | P243: =ROUND(Table20[[#This Row],[Total Expenses]] / $B$4 * 100, 2) -> 2.56
A244: sheena-related | B244: 150 | C244: 1 | D244: 7050 | E244: 3 | F244: 7200 | G244: 4 | I244: Supa | J244: 6154 | K244: 66 | L244: 6154 | M244: 66 | N244: 8 | O244: =ROUND(Table20[[#This Row],[Sum of G-cash Expenses]]/Table20[[#This Row],[Total Expenses]] * 100, 2) -> 100 | P244: =ROUND(Table20[[#This Row],[Total Expenses]] / $B$4 * 100, 2) -> 2.4
A245: ref (hulog) | D245: 7000 | E245: 1 | F245: 7000 | G245: 1 | I245: monitor | L245: 5490 | M245: 1 | N245: 9 | O245: =ROUND(Table20[[#This Row],[Sum of G-cash Expenses]]/Table20[[#This Row],[Total Expenses]] * 100, 2) -> 0 | P245: =ROUND(Table20[[#This Row],[Total Expenses]] / $B$4 * 100, 2) -> 2.14
A246: Pamasahe | D246: 6587 | E246: 87 | F246: 6587 | G246: 87 | I246: wifi load (magic data) | J246: 4494 | K246: 7 | L246: 4494 | M246: 7 | N246: 10 | O246: =ROUND(Table20[[#This Row],[Sum of G-cash Expenses]]/Table20[[#This Row],[Total Expenses]] * 100, 2) -> 100 | P246: =ROUND(Table20[[#This Row],[Total Expenses]] / $B$4 * 100, 2) -> 1.75
A247: Supa | B247: 6154 | C247: 66 | F247: 6154 | G247: 66 | I247: handa (birthday) | L247: 4000 | M247: 1 | N247: 11 | O247: =ROUND(Table20[[#This Row],[Sum of G-cash Expenses]]/Table20[[#This Row],[Total Expenses]] * 100, 2) -> 0 | P247: =ROUND(Table20[[#This Row],[Total Expenses]] / $B$4 * 100, 2) -> 1.56
A248: monitor | D248: 5490 | E248: 1 | F248: 5490 | G248: 1 | I248: wifi load (family access) | J248: 3981 | K248: 20 | L248: 3981 | M248: 20 | N248: 12 | O248: =ROUND(Table20[[#This Row],[Sum of G-cash Expenses]]/Table20[[#This Row],[Total Expenses]] * 100, 2) -> 100 | P248: =ROUND(Table20[[#This Row],[Total Expenses]] / $B$4 * 100, 2) -> 1.55
A249: wifi load (magic data) | B249: 4494 | C249: 7 | F249: 4494 | G249: 7 | I249: Kape | L249: 3800 | M249: 17 | N249: 13 | O249: =ROUND(Table20[[#This Row],[Sum of G-cash Expenses]]/Table20[[#This Row],[Total Expenses]] * 100, 2) -> 0 | P249: =ROUND(Table20[[#This Row],[Total Expenses]] / $B$4 * 100, 2) -> 1.48
A250: handa (birthday) | D250: 4000 | E250: 1 | F250: 4000 | G250: 1 | I250: battery | L250: 3600 | M250: 1 | N250: 14 | O250: =ROUND(Table20[[#This Row],[Sum of G-cash Expenses]]/Table20[[#This Row],[Total Expenses]] * 100, 2) -> 0 | P250: =ROUND(Table20[[#This Row],[Total Expenses]] / $B$4 * 100, 2) -> 1.4
A251: wifi load (family access) | B251: 3981 | C251: 20 | F251: 3981 | G251: 20 | I251: aragmot | L251: 3340 | M251: 8 | N251: 15 | O251: =ROUND(Table20[[#This Row],[Sum of G-cash Expenses]]/Table20[[#This Row],[Total Expenses]] * 100, 2) -> 0 | P251: =ROUND(Table20[[#This Row],[Total Expenses]] / $B$4 * 100, 2) -> 1.3
A252: Kape | D252: 3800 | E252: 17 | F252: 3800 | G252: 17 | I252: hatag kanda mama | L252: 3000 | M252: 1 | N252: 16 | O252: =ROUND(Table20[[#This Row],[Sum of G-cash Expenses]]/Table20[[#This Row],[Total Expenses]] * 100, 2) -> 0 | P252: =ROUND(Table20[[#This Row],[Total Expenses]] / $B$4 * 100, 2) -> 1.17
A253: battery | D253: 3600 | E253: 1 | F253: 3600 | G253: 1 | I253: irimnon | L253: 2990 | M253: 7 | N253: 17 | O253: =ROUND(Table20[[#This Row],[Sum of G-cash Expenses]]/Table20[[#This Row],[Total Expenses]] * 100, 2) -> 0 | P253: =ROUND(Table20[[#This Row],[Total Expenses]] / $B$4 * 100, 2) -> 1.16
A254: aragmot | D254: 3340 | E254: 8 | F254: 3340 | G254: 8 | I254: SSD | L254: 2900 | M254: 1 | N254: 18 | O254: =ROUND(Table20[[#This Row],[Sum of G-cash Expenses]]/Table20[[#This Row],[Total Expenses]] * 100, 2) -> 0 | P254: =ROUND(Table20[[#This Row],[Total Expenses]] / $B$4 * 100, 2) -> 1.13
A255: hatag kanda mama | D255: 3000 | E255: 1 | F255: 3000 | G255: 1 | I255: Spotify | J255: 2823 | K255: 12 | L255: 2823 | M255: 12 | N255: 19 | O255: =ROUND(Table20[[#This Row],[Sum of G-cash Expenses]]/Table20[[#This Row],[Total Expenses]] * 100, 2) -> 100 | P255: =ROUND(Table20[[#This Row],[Total Expenses]] / $B$4 * 100, 2) -> 1.1
A256: irimnon | D256: 2990 | E256: 7 | F256: 2990 | G256: 7 | I256: laptop keyboard | L256: 2600 | M256: 1 | N256: 20 | O256: =ROUND(Table20[[#This Row],[Sum of G-cash Expenses]]/Table20[[#This Row],[Total Expenses]] * 100, 2) -> 0 | P256: =ROUND(Table20[[#This Row],[Total Expenses]] / $B$4 * 100, 2) -> 1.01
A257: SSD | D257: 2900 | E257: 1 | F257: 2900 | G257: 1
A258: Spotify | B258: 2823 | C258: 12 | F258: 2823 | G258: 12
A259: laptop keyboard | D259: 2600 | E259: 1 | F259: 2600 | G259: 1 | I259: The G-cash Expenses in Top 20 Expenses | N259: *Helper Table
A260: gaming chair | D260: 2542 | E260: 1 | F260: 2542 | G260: 1 | I260: Row Labels | J260: Ranking | K260: Sum of Sum of G-cash Expenses | L260: Sum of Count of G-cash | N260: Detail | O260: Rank | P260: Sum | Q260: Count
A261: Tito patron assistance | D261: 2000 | E261: 1 | F261: 2000 | G261: 1 | I261: Supa | J261: 8 | K261: 6154 | L261: 66 | N261: Supa | O261: 8 | P261: 6154 | Q261: 66
A262: labor | D262: 2000 | E262: 1 | F262: 2000 | G262: 1 | I262: wifi load (magic data) | J262: 10 | K262: 4494 | L262: 7 | N262: wifi load (magic data) | O262: 10 | P262: 4494 | Q262: 7
A263: bluetooth speaker | D263: 1990 | E263: 1 | F263: 1990 | G263: 1 | I263: wifi load (family access) | J263: 12 | K263: 3981 | L263: 20 | N263: wifi load (family access) | O263: 12 | P263: 3981 | Q263: 20
A264: Genshin Welkin | B264: 1960 | C264: 7 | F264: 1960 | G264: 7 | I264: Spotify | J264: 19 | K264: 2823 | L264: 12 | N264: Spotify | O264: 19 | P264: 2823 | Q264: 12
A265: Pamahaw | D265: 1953 | E265: 17 | F265: 1953 | G265: 17 | I265: sheena-related | J265: 5 | K265: 150 | L265: 1 | N265: sheena-related | O265: 5 | P265: 150 | Q265: 1
A266: soft drinks | D266: 1850 | E266: 10 | F266: 1850 | G266: 10 | I266: Grand Total | J266: 54 | K266: 17602 | L266: 106
A267: medisina | D267: 1723 | E267: 2 | F267: 1723 | G267: 2
A268: steam | B268: 1705 | C268: 7 | F268: 1705 | G268: 7
...

Sheet data_visualization
A1: Navigate: | B1: Dashboard | C1: Findings | D1: Pivot & Derived Tables | E1: Analysis & Diagnosis | F1: Data Visualization | G1: Cleaned Data Source | H1: Raw Data Source

Sheet Nov 24 & Dec 24
A1: trans_no | B1: date | C1: details | D1: amount | E1: transaction | F1: transaction_mode | G1: month | H1: year | I1: cleaned_detail
A2: 1 | B2: 45183 | C2: サラリー | D2: 17732 | E2: Income | F2: Bank | G2: =MONTH(cleaned_personal_finance_data15[[#This Row],[date]]) -> 9 | H2: =YEAR(cleaned_personal_finance_data15[[#This Row],[date]]) -> 2023 | I2: salary
A3: 2 | B3: 45208 | C3: サラリー | D3: 12754 | E3: Income | F3: Bank | G3: =MONTH(cleaned_personal_finance_data15[[#This Row],[date]]) -> 10 | H3: =YEAR(cleaned_personal_finance_data15[[#This Row],[date]]) -> 2023 | I3: salary
A4: 3 | B4: 45214 | C4: bank withdraw | D4: 26142 | E4: Withdraw | F4: Bank | G4: =MONTH(cleaned_personal_finance_data15[[#This Row],[date]]) -> 10 | H4: =YEAR(cleaned_personal_finance_data15[[#This Row],[date]]) -> 2023 | I4: bank withdraw
A5: 4 | B5: 45214 | C5: stash deposit | D5: 26142 | E5: Deposit | F5: Stash | G5: =MONTH(cleaned_personal_finance_data15[[#This Row],[date]]) -> 10 | H5: =YEAR(cleaned_personal_finance_data15[[#This Row],[date]]) -> 2023 | I5: stash deposit
A6: 5 | B6: 45230 | C6: サラリー | D6: 12834 | E6: Income | F6: Bank | G6: =MONTH(cleaned_personal_finance_data15[[#This Row],[date]]) -> 10 | H6: =YEAR(cleaned_personal_finance_data15[[#This Row],[date]]) -> 2023 | I6: salary
A7: 6 | B7: 45235 | C7: Monthly gasoline (oct) | D7: 2550 | E7: Expenses | F7: Stash | G7: =MONTH(cleaned_personal_finance_data15[[#This Row],[date]]) -> 11 | H7: =YEAR(cleaned_personal_finance_data15[[#This Row],[date]]) -> 2023 | I7: Gasolina
A8: 7 | B8: 45235 | C8: Balay (Oct) | D8: 5000 | E8: Expenses | F8: Stash | G8: =MONTH(cleaned_personal_finance_data15[[#This Row],[date]]) -> 11 | H8: =YEAR(cleaned_personal_finance_data15[[#This Row],[date]]) -> 2023 | I8: balay
A9: 8 | B9: 45235 | C9: Tahong harvest | D9: 12560 | E9: Income | F9: Stash | G9: =MONTH(cleaned_personal_finance_data15[[#This Row],[date]]) -> 11 | H9: =YEAR(cleaned_personal_finance_data15[[#This Row],[date]]) -> 2023 | I9: Tahong harvest
A10: 9 | B10: 45235 | C10: pansit canton | D10: 56 | E10: Expenses | F10: Stash | G10: =MONTH(cleaned_personal_finance_data15[[#This Row],[date]]) -> 11 | H10: =YEAR(cleaned_personal_finance_data15[[#This Row],[date]]) -> 2023 | I10: pansit canton
A11: 10 | B11: 45235 | C11: monay | D11: 30 | E11: Expenses | F11: Stash | G11: =MONTH(cleaned_personal_finance_data15[[#This Row],[date]]) -> 11 | H11: =YEAR(cleaned_personal_finance_data15[[#This Row],[date]]) -> 2023 | I11: Monay (1 putos)
A12: 11 | B12: 45235 | C12: Gcash cash-in | D12: 2010 | E12: Withdraw | F12: Stash | G12: =MONTH(cleaned_personal_finance_data15[[#This Row],[date]]) -> 11 | H12: =YEAR(cleaned_personal_finance_data15[[#This Row],[date]]) -> 2023 | I12: Gcash cash-in
A13: 12 | B13: 45235 | C13: Gcash cash-in | D13: 2010 | E13: Deposit | F13: G-cash | G13: =MONTH(cleaned_personal_finance_data15[[#This Row],[date]]) -> 11 | H13: =YEAR(cleaned_personal_finance_data15[[#This Row],[date]]) -> 2023 | I13: Gcash cash-in
... A672: 671 | B672: 45687 | C672: サラリー | D672: 13202 | E672: Income | F672: Bank | G672: =MONTH(cleaned_personal_finance_data15[[#This Row],[date]]) -> 1 | H672: =YEAR(cleaned_personal_finance_data15[[#This Row],[date]]) -> 2025 | I672: salary

Sheet Expenses_table
A1: trans_no | B1: date | C1: details | D1: amount | E1: transaction | F1: transaction_mode | G1: month | H1: year | I1: cleaned_detail
A2: 1 | B2: 45183 | C2: サラリー | D2: 17732 | E2: Income | F2: Bank | G2: =MONTH(cleaned_personal_finance_data3[[#This Row],[date]]) -> 9 | H2: =YEAR(cleaned_personal_finance_data3[[#This Row],[date]]) -> 2023 | I2: salary
A3: 2 | B3: 45208 | C3: サラリー | D3: 12754 | E3: Income | F3: Bank | G3: =MONTH(cleaned_personal_finance_data3[[#This Row],[date]]) -> 10 | H3: =YEAR(cleaned_personal_finance_data3[[#This Row],[date]]) -> 2023 | I3: salary
A4: 3 | B4: 45214 | C4: bank withdraw | D4: 26142 | E4: Withdraw | F4: Bank | G4: =MONTH(cleaned_personal_finance_data3[[#This Row],[date]]) -> 10 | H4: =YEAR(cleaned_personal_finance_data3[[#This Row],[date]]) -> 2023 | I4: bank withdraw
A5: 4 | B5: 45214 | C5: stash deposit | D5: 26142 | E5: Deposit | F5: Stash | G5: =MONTH(cleaned_personal_finance_data3[[#This Row],[date]]) -> 10 | H5: =YEAR(cleaned_personal_finance_data3[[#This Row],[date]]) -> 2023 | I5: stash deposit
A6: 5 | B6: 45230 | C6: サラリー | D6: 12834 | E6: Income | F6: Bank | G6: =MONTH(cleaned_personal_finance_data3[[#This Row],[date]]) -> 10 | H6: =YEAR(cleaned_personal_finance_data3[[#This Row],[date]]) -> 2023 | I6: salary
A7: 6 | B7: 45235 | C7: Monthly gasoline (oct) | D7: 2550 | E7: Expenses | F7: Stash | G7: =MONTH(cleaned_personal_finance_data3[[#This Row],[date]]) -> 11 | H7: =YEAR(cleaned_personal_finance_data3[[#This Row],[date]]) -> 2023 | I7: Gasolina
A8: 7 | B8: 45235 | C8: Balay (Oct) | D8: 5000 | E8: Expenses | F8: Stash | G8: =MONTH(cleaned_personal_finance_data3[[#This Row],[date]]) -> 11 | H8: =YEAR(cleaned_personal_finance_data3[[#This Row],[date]]) -> 2023 | I8: balay
A9: 8 | B9: 45235 | C9: Tahong harvest | D9: 12560 | E9: Income | F9: Stash | G9: =MONTH(cleaned_personal_finance_data3[[#This Row],[date]]) -> 11 | H9: =YEAR(cleaned_personal_finance_data3[[#This Row],[date]]) -> 2023 | I9: Tahong harvest
A10: 9 | B10: 45235 | C10: pansit canton | D10: 56 | E10: Expenses | F10: Stash | G10: =MONTH(cleaned_personal_finance_data3[[#This Row],[date]]) -> 11 | H10: =YEAR(cleaned_personal_finance_data3[[#This Row],[date]]) -> 2023 | I10: pansit canton
A11: 10 | B11: 45235 | C11: monay | D11: 30 | E11: Expenses | F11: Stash | G11: =MONTH(cleaned_personal_finance_data3[[#This Row],[date]]) -> 11 | H11: =YEAR(cleaned_personal_finance_data3[[#This Row],[date]]) -> 2023 | I11: Monay (1 putos)
A12: 11 | B12: 45235 | C12: Gcash cash-in | D12: 2010 | E12: Withdraw | F12: Stash | G12: =MONTH(cleaned_personal_finance_data3[[#This Row],[date]]) -> 11 | H12: =YEAR(cleaned_personal_finance_data3[[#This Row],[date]]) -> 2023 | I12: Gcash cash-in
A13: 12 | B13: 45235 | C13: Gcash cash-in | D13: 2010 | E13: Deposit | F13: G-cash | G13: =MONTH(cleaned_personal_finance_data3[[#This Row],[date]]) -> 11 | H13: =YEAR(cleaned_personal_finance_data3[[#This Row],[date]]) -> 2023 | I13: Gcash cash-in
... A672: 671 | B672: 45687 | C672: サラリー | D672: 13202 | E672: Income | F672: Bank | G672: =MONTH(cleaned_personal_finance_data3[[#This Row],[date]]) -> 1 | H672: =YEAR(cleaned_personal_finance_data3[[#This Row],[date]]) -> 2025 | I672: salary

Sheet Income_table
A1: trans_no | B1: date | C1: details | D1: amount | E1: transaction | F1: transaction_mode | G1: month | H1: year | I1: cleaned_detail
A2: 1 | B2: 45183 | C2: サラリー | D2: 17732 | E2: Income | F2: Bank | G2: =MONTH(cleaned_personal_finance_data4[[#This Row],[date]]) -> 9 | H2: =YEAR(cleaned_personal_finance_data4[[#This Row],[date]]) -> 2023 | I2: salary
A3: 2 | B3: 45208 | C3: サラリー | D3: 12754 | E3: Income | F3: Bank | G3: =MONTH(cleaned_personal_finance_data4[[#This Row],[date]]) -> 10 | H3: =YEAR(cleaned_personal_finance_data4[[#This Row],[date]]) -> 2023 | I3: salary
A4: 3 | B4: 45214 | C4: bank withdraw | D4: 26142 | E4: Withdraw | F4: Bank | G4: =MONTH(cleaned_personal_finance_data4[[#This Row],[date]]) -> 10 | H4: =YEAR(cleaned_personal_finance_data4[[#This Row],[date]]) -> 2023 | I4: bank withdraw
A5: 4 | B5: 45214 | C5: stash deposit | D5: 26142 | E5: Deposit | F5: Stash | G5: =MONTH(cleaned_personal_finance_data4[[#This Row],[date]]) -> 10 | H5: =YEAR(cleaned_personal_finance_data4[[#This Row],[date]]) -> 2023 | I5: stash deposit
A6: 5 | B6: 45230 | C6: サラリー | D6: 12834 | E6: Income | F6: Bank | G6: =MONTH(cleaned_personal_finance_data4[[#This Row],[date]]) -> 10 | H6: =YEAR(cleaned_personal_finance_data4[[#This Row],[date]]) -> 2023 | I6: salary
A7: 6 | B7: 45235 | C7: Monthly gasoline (oct) | D7: 2550 | E7: Expenses | F7: Stash | G7: =MONTH(cleaned_personal_finance_data4[[#This Row],[date]]) -> 11 | H7: =YEAR(cleaned_personal_finance_data4[[#This Row],[date]]) -> 2023 | I7: Gasolina
A8: 7 | B8: 45235 | C8: Balay (Oct) | D8: 5000 | E8: Expenses | F8: Stash | G8: =MONTH(cleaned_personal_finance_data4[[#This Row],[date]]) -> 11 | H8: =YEAR(cleaned_personal_finance_data4[[#This Row],[date]]) -> 2023 | I8: balay
A9: 8 | B9: 45235 | C9: Tahong harvest | D9: 12560 | E9: Income | F9: Stash | G9: =MONTH(cleaned_personal_finance_data4[[#This Row],[date]]) -> 11 | H9: =YEAR(cleaned_personal_finance_data4[[#This Row],[date]]) -> 2023 | I9: Tahong harvest
A10: 9 | B10: 45235 | C10: pansit canton | D10: 56 | E10: Expenses | F10: Stash | G10: =MONTH(cleaned_personal_finance_data4[[#This Row],[date]]) -> 11 | H10: =YEAR(cleaned_personal_finance_data4[[#This Row],[date]]) -> 2023 | I10: pansit canton
A11: 10 | B11: 45235 | C11: monay | D11: 30 | E11: Expenses | F11: Stash | G11: =MONTH(cleaned_personal_finance_data4[[#This Row],[date]]) -> 11 | H11: =YEAR(cleaned_personal_finance_data4[[#This Row],[date]]) -> 2023 | I11: Monay (1 putos)
A12: 11 | B12: 45235 | C12: Gcash cash-in | D12: 2010 | E12: Withdraw | F12: Stash | G12: =MONTH(cleaned_personal_finance_data4[[#This Row],[date]]) -> 11 | H12: =YEAR(cleaned_personal_finance_data4[[#This Row],[date]]) -> 2023 | I12: Gcash cash-in
A13: 12 | B13: 45235 | C13: Gcash cash-in | D13: 2010 | E13: Deposit | F13: G-cash | G13: =MONTH(cleaned_personal_finance_data4[[#This Row],[date]]) -> 11 | H13: =YEAR(cleaned_personal_finance_data4[[#This Row],[date]]) -> 2023 | I13: Gcash cash-in
... A672: 671 | B672: 45687 | C672: サラリー | D672: 13202 | E672: Income | F672: Bank | G672: =MONTH(cleaned_personal_finance_data4[[#This Row],[date]]) -> 1 | H672: =YEAR(cleaned_personal_finance_data4[[#This Row],[date]]) -> 2025 | I672: salary

Sheet Gcash_expenses
A1: trans_no | B1: date | C1: detail | D1: amount | E1: transaction | F1: transaction_mode | G1: day | H1: year | I1: cleaned_detail
A2: 15 | B2: 45236 | C2: Spotify | D2: 194 | E2: Expenses | F2: G-cash | G2: 11 | H2: 2023 | I2: Spotify
A3: 19 | B3: 45243 | C3: Supa | D3: 25 | E3: Expenses | F3: G-cash | G3: 11 | H3: 2023 | I3: Supa
A4: 20 | B4: 45243 | C4: Supa | D4: 125 | E4: Expenses | F4: G-cash | G4: 11 | H4: 2023 | I4: Supa
A5: 22 | B5: 45245 | C5: Supa | D5: 125 | E5: Expenses | F5: G-cash | G5: 11 | H5: 2023 | I5: Supa
A6: 30 | B6: 45252 | C6: YT Membership | D6: 129 | E6: Expenses | F6: G-cash | G6: 11 | H6: 2023 | I6: YT Membership
A7: 31 | B7: 45252 | C7: Genshin Welkin | D7: 280 | E7: Expenses | F7: G-cash | G7: 11 | H7: 2023 | I7: Genshin Welkin
A8: 32 | B8: 45253 | C8: Supa | D8: 125 | E8: Expenses | F8: G-cash | G8: 11 | H8: 2023 | I8: Supa
A9: 34 | B9: 45262 | C9: Supa | D9: 125 | E9: Expenses | F9: G-cash | G9: 12 | H9: 2023 | I9: Supa
A10: 38 | B10: 45266 | C10: Spotify | D10: 239 | E10: Expenses | F10: G-cash | G10: 12 | H10: 2023 | I10: Spotify
A11: 40 | B11: 45268 | C11: Supa | D11: 125 | E11: Expenses | F11: G-cash | G11: 12 | H11: 2023 | I11: Supa
A12: 58 | B12: 45274 | C12: wifi load (magic data) | D12: 599 | E12: Expenses | F12: G-cash | G12: 12 | H12: 2023 | I12: wifi load (magic data)
A13: 75 | B13: 45278 | C13: Genshin Welkin | D13: 280 | E13: Expenses | F13: G-cash | G13: 12 | H13: 2023 | I13: Genshin Welkin
... A139: 542 | B139: 45599 | C139: wifi load (family access) | D139: 199 | E139: Expenses | F139: G-cash | G139: 11 | H139: 2024 | I139: wifi load (family access)

Sheet Supa Expenses
A1: trans_no | B1: date | C1: details | D1: amount | E1: transaction | F1: transaction_mode | G1: month | H1: year | I1: cleaned_detail | N1: amount
A2: 19 | B2: 45243 | C2: Supa | D2: 25 | E2: Expenses | F2: G-cash | G2: 11 | H2: 2023 | I2: Supa | N2: 25
A3: 20 | B3: 45243 | C3: Supa | D3: 125 | E3: Expenses | F3: G-cash | G3: 11 | H3: 2023 | I3: Supa | N3: 125
A4: 22 | B4: 45245 | C4: Supa | D4: 125 | E4: Expenses | F4: G-cash | G4: 11 | H4: 2023 | I4: Supa | N4: 125
A5: 32 | B5: 45253 | C5: Supa | D5: 125 | E5: Expenses | F5: G-cash | G5: 11 | H5: 2023 | I5: Supa | N5: 125
A6: 34 | B6: 45262 | C6: Supa | D6: 125 | E6: Expenses | F6: G-cash | G6: 12 | H6: 2023 | I6: Supa | N6: 125
A7: 40 | B7: 45268 | C7: Supa | D7: 125 | E7: Expenses | F7: G-cash | G7: 12 | H7: 2023 | I7: Supa | N7: 125
A8: 111 | B8: 45298 | C8: Supa | D8: 125 | E8: Expenses | F8: G-cash | G8: 1 | H8: 2024 | I8: Supa | N8: 125
A9: 112 | B9: 45298 | C9: Supa | D9: 50 | E9: Expenses | F9: G-cash | G9: 1 | H9: 2024 | I9: Supa | N9: 50
A10: 117 | B10: 45299 | C10: Supa | D10: 25 | E10: Expenses | F10: G-cash | G10: 1 | H10: 2024 | I10: Supa | N10: 25
A11: 118 | B11: 45300 | C11: Supa | D11: 50 | E11: Expenses | F11: G-cash | G11: 1 | H11: 2024 | I11: Supa | N11: 50
A12: 135 | B12: 45306 | C12: Supa | D12: 125 | E12: Expenses | F12: G-cash | G12: 1 | H12: 2024 | I12: Supa | N12: 125
A13: 137 | B13: 45309 | C13: Supa | D13: 125 | E13: Expenses | F13: G-cash | G13: 1 | H13: 2024 | I13: Supa | N13: 125
... A67: 534 | B67: 45590 | C67: Supa | D67: 25 | E67: Expenses | F67: G-cash | G67: 10 | H67: 2024 | I67: Supa | N67: 25

Sheet query
A1: Income Data | M1: G-cash Transactions | Y1: G-cash Expenses | AK1: Supa Transactions
A2: trans_no | B2: date | C2: detail | D2: amount | E2: transaction | F2: transaction_mode | G2: day | H2: year | I2: cleaned_detail | M2: trans_no | N2: date | O2: detail | P2: amount | Q2: transaction | R2: transaction_mode | S2: day | T2: year | U2: cleaned_detail | Y2: trans_no | Z2: date | AA2: detail | AB2: amount | AC2: transaction | AD2: transaction_mode | AE2: day | AF2: year | AG2: cleaned_detail | AK2: trans_no | AL2: date | AM2: detail | AN2: amount | AO2: transaction | AP2: transaction_mode | AQ2: day | AR2: year | AS2: cleaned_detail
A3: {=_xlfn._xlws.FILTER(cleaned_personal_finance_data[], cleaned_personal_finance_data[transaction]="Income", "")} -> 1 | B3: 45183 | C3: サラリー | D3: 17732 | E3: Income | F3: Bank | G3: 9 | H3: 2023 | I3: salary | M3: {=_xlfn._xlws.FILTER(cleaned_personal_finance_data[], cleaned_personal_finance_data[transaction_mode]="G-cash", "")} -> 12 | N3: 45235 | O3: Gcash cash-in | P3: 2010 | Q3: Deposit | R3: G-cash | S3: 11 | T3: 2023 | U3: Gcash cash-in | Y3: {=_xlfn._xlws.FILTER(cleaned_personal_finance_data[], (cleaned_personal_finance_data[transaction_mode]="G-cash") * (cleaned_personal_finance_data[transaction]="Expenses"), "")} -> 15 | Z3: 45236 | AA3: Spotify | AB3: 194 | AC3: Expenses | AD3: G-cash | AE3: 11 | AF3: 2023 | AG3: Spotify | AK3: {=_xlfn._xlws.FILTER(cleaned_personal_finance_data[], (cleaned_personal_finance_data[transaction_mode]="G-cash") * (cleaned_personal_finance_data[transaction]="Expenses") * (cleaned_personal_finance_data[cleaned_detail]="Supa"), "")} -> 19 | AL3: 45243 | AM3: Supa | AN3: 25 | AO3: Expenses | AP3: G-cash | AQ3: 11 | AR3: 2023 | AS3: Supa | AW3: {=_xlfn._xlws.FILTER(cleaned_personal_finance_data[], (cleaned_personal_finance_data[transaction_mode]="G-cash") * (cleaned_personal_finance_data[transaction]="Expenses") * (cleaned_personal_finance_data[cleaned_detail]="Supa"), "")} -> 19 | AX3: 45243 | AY3: Supa | AZ3: 25 | BA3: Expenses | BB3: G-cash | BC3: 11 | BD3: 2023 | BE3: Supa
A4: 2 | B4: 45208 | C4: サラリー | D4: 12754 | E4: Income | F4: Bank | G4: 10 | H4: 2023 | I4: salary | M4: 15 | N4: 45236 | O4: Spotify | P4: 194 | Q4: Expenses | R4: G-cash | S4: 11 | T4: 2023 | U4: Spotify | Y4: 19 | Z4: 45243 | AA4: Supa | AB4: 25 | AC4: Expenses | AD4: G-cash | AE4: 11 | AF4: 2023 | AG4: Supa | AK4: 20 | AL4: 45243 | AM4: Supa | AN4: 125 | AO4: Expenses | AP4: G-cash | AQ4: 11 | AR4: 2023 | AS4: Supa | AW4: 20 | AX4: 45243 | AY4: Supa | AZ4: 125 | BA4: Expenses | BB4: G-cash | BC4: 11 | BD4: 2023 | BE4: Supa
A5: 5 | B5: 45230 | C5: サラリー | D5: 12834 | E5: Income | F5: Bank | G5: 10 | H5: 2023 | I5: salary | M5: 19 | N5: 45243 | O5: Supa | P5: 25 | Q5: Expenses | R5: G-cash | S5: 11 | T5: 2023 | U5: Supa | Y5: 20 | Z5: 45243 | AA5: Supa | AB5: 125 | AC5: Expenses | AD5: G-cash | AE5: 11 | AF5: 2023 | AG5: Supa | AK5: 22 | AL5: 45245 | AM5: Supa | AN5: 125 | AO5: Expenses | AP5: G-cash | AQ5: 11 | AR5: 2023 | AS5: Supa | AW5: 22 | AX5: 45245 | AY5: Supa | AZ5: 125 | BA5: Expenses | BB5: G-cash | BC5: 11 | BD5: 2023 | BE5: Supa
A6: 8 | B6: 45235 | C6: Tahong harvest | D6: 12560 | E6: Income | F6: Stash | G6: 11 | H6: 2023 | I6: Tahong harvest | M6: 20 | N6: 45243 | O6: Supa | P6: 125 | Q6: Expenses | R6: G-cash | S6: 11 | T6: 2023 | U6: Supa | Y6: 22 | Z6: 45245 | AA6: Supa | AB6: 125 | AC6: Expenses | AD6: G-cash | AE6: 11 | AF6: 2023 | AG6: Supa | AK6: 32 | AL6: 45253 | AM6: Supa | AN6: 125 | AO6: Expenses | AP6: G-cash | AQ6: 11 | AR6: 2023 | AS6: Supa | AW6: 32 | AX6: 45253 | AY6: Supa | AZ6: 125 | BA6: Expenses | BB6: G-cash | BC6: 11 | BD6: 2023 | BE6: Supa
A7: 28 | B7: 45248 | C7: Income (with bonus?) | D7: 44732 | E7: Income | F7: Bank | G7: 11 | H7: 2023 | I7: Income (with bonus?) | M7: 22 | N7: 45245 | O7: Supa | P7: 125 | Q7: Expenses | R7: G-cash | S7: 11 | T7: 2023 | U7: Supa | Y7: 30 | Z7: 45252 | AA7: YT Membership | AB7: 129 | AC7: Expenses | AD7: G-cash | AE7: 11 | AF7: 2023 | AG7: YT Membership | AK7: 34 | AL7: 45262 | AM7: Supa | AN7: 125 | AO7: Expenses | AP7: G-cash | AQ7: 12 | AR7: 2023 | AS7: Supa | AW7: 34 | AX7: 45262 | AY7: Supa | AZ7: 125 | BA7: Expenses | BB7: G-cash | BC7: 12 | BD7: 2023 | BE7: Supa
A8: 33 | B8: 45260 | C8: サラリー | D8: 12734 | E8: Income | F8: Bank | G8: 11 | H8: 2023 | I8: salary | M8: 30 | N8: 45252 | O8: YT Membership | P8: 129 | Q8: Expenses | R8: G-cash | S8: 11 | T8: 2023 | U8: YT Membership | Y8: 31 | Z8: 45252 | AA8: Genshin Welkin | AB8: 280 | AC8: Expenses | AD8: G-cash | AE8: 11 | AF8: 2023 | AG8: Genshin Welkin | AK8: 40 | AL8: 45268 | AM8: Supa | AN8: 125 | AO8: Expenses | AP8: G-cash | AQ8: 12 | AR8: 2023 | AS8: Supa | AW8: 40 | AX8: 45268 | AY8: Supa | AZ8: 125 | BA8: Expenses | BB8: G-cash | BC8: 12 | BD8: 2023 | BE8: Supa
A9: 55 | B9: 45274 | C9: サラリー | D9: 12732 | E9: Income | F9: Bank | G9: 12 | H9: 2023 | I9: salary | M9: 31 | N9: 45252 | O9: Genshin Welkin | P9: 280 | Q9: Expenses | R9: G-cash | S9: 11 | T9: 2023 | U9: Genshin Welkin | Y9: 32 | Z9: 45253 | AA9: Supa | AB9: 125 | AC9: Expenses | AD9: G-cash | AE9: 11 | AF9: 2023 | AG9: Supa | AK9: 111 | AL9: 45298 | AM9: Supa | AN9: 125 | AO9: Expenses | AP9: G-cash | AQ9: 1 | AR9: 2024 | AS9: Supa | AW9: 111 | AX9: 45298 | AY9: Supa | AZ9: 125 | BA9: Expenses | BB9: G-cash | BC9: 1 | BD9: 2024 | BE9: Supa
A10: 86 | B10: 45283 | C10: SRI | D10: 18000 | E10: Income | F10: Stash | G10: 12 | H10: 2023 | I10: SRI | M10: 32 | N10: 45253 | O10: Supa | P10: 125 | Q10: Expenses | R10: G-cash | S10: 11 | T10: 2023 | U10: Supa | Y10: 34 | Z10: 45262 | AA10: Supa | AB10: 125 | AC10: Expenses | AD10: G-cash | AE10: 12 | AF10: 2023 | AG10: Supa | AK10: 112 | AL10: 45298 | AM10: Supa | AN10: 50 | AO10: Expenses | AP10: G-cash | AQ10: 1 | AR10: 2024 | AS10: Supa | AW10: 112 | AX10: 45298 | AY10: Supa | AZ10: 50 | BA10: Expenses | BB10: G-cash | BC10: 1 | BD10: 2024 | BE10: Supa
A11: 106 | B11: 45288 | C11: サラリー | D11: 12733 | E11: Income | F11: Bank | G11: 12 | H11: 2023 | I11: salary | M11: 34 | N11: 45262 | O11: Supa | P11: 125 | Q11: Expenses | R11: G-cash | S11: 12 | T11: 2023 | U11: Supa | Y11: 38 | Z11: 45266 | AA11: Spotify | AB11: 239 | AC11: Expenses | AD11: G-cash | AE11: 12 | AF11: 2023 | AG11: Spotify | AK11: 117 | AL11: 45299 | AM11: Supa | AN11: 25 | AO11: Expenses | AP11: G-cash | AQ11: 1 | AR11: 2024 | AS11: Supa | AW11: 117 | AX11: 45299 | AY11: Supa | AZ11: 25 | BA11: Expenses | BB11: G-cash | BC11: 1 | BD11: 2024 | BE11: Supa
A12: 133 | B12: 45305 | C12: サラリー | D12: 12732 | E12: Income | F12: Bank | G12: 1 | H12: 2024 | I12: salary | M12: 38 | N12: 45266 | O12: Spotify | P12: 239 | Q12: Expenses | R12: G-cash | S12: 12 | T12: 2023 | U12: Spotify | Y12: 40 | Z12: 45268 | AA12: Supa | AB12: 125 | AC12: Expenses | AD12: G-cash | AE12: 12 | AF12: 2023 | AG12: Supa | AK12: 118 | AL12: 45300 | AM12: Supa | AN12: 50 | AO12: Expenses | AP12: G-cash | AQ12: 1 | AR12: 2024 | AS12: Supa | AW12: 118 | AX12: 45300 | AY12: Supa | AZ12: 50 | BA12: Expenses | BB12: G-cash | BC12: 1 | BD12: 2024 | BE12: Supa
A13: 146 | B13: 45319 | C13: サラリー | D13: 12734 | E13: Income | F13: Bank | G13: 1 | H13: 2024 | I13: salary | M13: 40 | N13: 45268 | O13: Supa | P13: 125 | Q13: Expenses | R13: G-cash | S13: 12 | T13: 2023 | U13: Supa | Y13: 58 | Z13: 45274 | AA13: wifi load (magic data) | AB13: 599 | AC13: Expenses | AD13: G-cash | AE13: 12 | AF13: 2023 | AG13: wifi load (magic data) | AK13: 135 | AL13: 45306 | AM13: Supa | AN13: 125 | AO13: Expenses | AP13: G-cash | AQ13: 1 | AR13: 2024 | AS13: Supa | AW13: 135 | AX13: 45306 | AY13: Supa | AZ13: 125 | BA13: Expenses | BB13: G-cash | BC13: 1 | BD13: 2024 | BE13: Supa
A14: 202 | B14: 45337 | C14: サラリー | D14: 12597 | E14: Income | F14: Bank | G14: 2 | H14: 2024 | I14: salary | M14: 56 | N14: 45274 | O14: Gcash cash-in | P14: 3000 | Q14: Withdraw | R14: G-cash | S14: 12 | T14: 2023 | U14: Gcash cash-in | Y14: 75 | Z14: 45278 | AA14: Genshin Welkin | AB14: 280 | AC14: Expenses | AD14: G-cash | AE14: 12 | AF14: 2023 | AG14: Genshin Welkin | AK14: 137 | AL14: 45309 | AM14: Supa | AN14: 125 | AO14: Expenses | AP14: G-cash | AQ14: 1 | AR14: 2024 | AS14: Supa | AW14: 137 | AX14: 45309 | AY14: Supa | AZ14: 125 | BA14: Expenses | BB14: G-cash | BC14: 1 | BD14: 2024 | BE14: Supa
A15: 221 | B15: 45351 | C15: さラリー | D15: 12598 | E15: Income | F15: Bank | G15: 2 | H15: 2024 | I15: salary | M15: 57 | N15: 45274 | O15: Gcash cash-in | P15: 3000 | Q15: Deposit | R15: G-cash | S15: 12 | T15: 2023 | U15: Gcash cash-in | Y15: 76 | Z15: 45279 | AA15: wifi load (family access) | AB15: 199 | AC15: Expenses | AD15: G-cash | AE15: 12 | AF15: 2023 | AG15: wifi load (family access) | AK15: 138 | AL15: 45310 | AM15: Supa | AN15: 125 | AO15: Expenses | AP15: G-cash | AQ15: 1 | AR15: 2024 | AS15: Supa | AW15: 138 | AX15: 45310 | AY15: Supa | AZ15: 125 | BA15: Expenses | BB15: G-cash | BC15: 1 | BD15: 2024 | BE15: Supa
... A46: 671 | B46: 45687 | C46: サラリー | D46: 13202 | E46: Income | F46: Bank | G46: 1 | H46: 2025 | I46: salary | M46: 164 | N46: 45323 | O46: Supa | P46: 50 | Q46: Expenses | R46: G-cash | S46: 2 | T46: 2024 | U46: Supa | Y46: 207 | Z46: 45338 | AA46: Steam (overcooked 2) | AB46: 199 | AC46: Expenses | AD46: G-cash | AE46: 2 | AF46: 2024 | AG46: steam | AK46: 353 | AL46: 45466 | AM46: Supa | AN46: 50 | AO46: Expenses | AP46: G-cash | AQ46: 6 | AR46: 2024 | AS46: Supa | AW46: 353 | AX46: 45466 | AY46: Supa | AZ46: 50 | BA46: Expenses | BB46: G-cash | BC46: 6 | BD46: 2024 | BE46: Supa
M47: 189 | N47: 45329 | O47: Gcash cash-in | P47: 3000 | Q47: Deposit | R47: G-cash | S47: 2 | T47: 2024 | U47: Gcash cash-in | Y47: 209 | Z47: 45343 | AA47: Genshin Welkin | AB47: 280 | AC47: Expenses | AD47: G-cash | AE47: 2 | AF47: 2024 | AG47: Genshin Welkin | AK47: 354 | AL47: 45466 | AM47: Supa | AN47: 50 | AO47: Expenses | AP47: G-cash | AQ47: 6 | AR47: 2024 | AS47: Supa | AW47: 354 | AX47: 45466 | AY47: Supa | AZ47: 50 | BA47: Expenses | BB47: G-cash | BC47: 6 | BD47: 2024 | BE47: Supa
M48: 191 | N48: 45329 | O48: Spotify | P48: 239 | Q48: Expenses | R48: G-cash | S48: 2 | T48: 2024 | U48: Spotify | Y48: 210 | Z48: 45344 | AA48: Supa | AB48: 129 | AC48: Expenses | AD48: G-cash | AE48: 2 | AF48: 2024 | AG48: Supa | AK48: 355 | AL48: 45466 | AM48: Supa | AN48: 125 | AO48: Expenses | AP48: G-cash | AQ48: 6 | AR48: 2024 | AS48: Supa | AW48: 355 | AX48: 45466 | AY48: Supa | AZ48: 125 | BA48: Expenses | BB48: G-cash | BC48: 6 | BD48: 2024 | BE48: Supa
M49: 194 | N49: 45331 | O49: wifi load (family access) | P49: 199 | Q49: Expenses | R49: G-cash | S49: 2 | T49: 2024 | U49: wifi load (family access) | Y49: 223 | Z49: 45353 | AA49: Supa | AB49: 125 | AC49: Expenses | AD49: G-cash | AE49: 3 | AF49: 2024 | AG49: Supa | AK49: 358 | AL49: 45470 | AM49: Supa | AN49: 50 | AO49: Expenses | AP49: G-cash | AQ49: 6 | AR49: 2024 | AS49: Supa | AW49: 358 | AX49: 45470 | AY49: Supa | AZ49: 50 | BA49: Expenses | BB49: G-cash | BC49: 6 | BD49: 2024 | BE49: Supa
M50: 195 | N50: 45331 | O50: Steam (Yakuza 0) | P50: 280 | Q50: Expenses | R50: G-cash | S50: 2 | T50: 2024 | U50: steam | Y50: 230 | Z50: 45356 | AA50: Supa | AB50: 50 | AC50: Expenses | AD50: G-cash | AE50: 3 | AF50: 2024 | AG50: Supa | AK50: 359 | AL50: 45470 | AM50: Supa | AN50: 50 | AO50: Expenses | AP50: G-cash | AQ50: 6 | AR50: 2024 | AS50: Supa | AW50: 359 | AX50: 45470 | AY50: Supa | AZ50: 50 | BA50: Expenses | BB50: G-cash | BC50: 6 | BD50: 2024 | BE50: Supa
M51: 196 | N51: 45331 | O51: wifi load (family access) | P51: 199 | Q51: Expenses | R51: G-cash | S51: 2 | T51: 2024 | U51: wifi load (family access) | Y51: 231 | Z51: 45356 | AA51: Supa | AB51: 125 | AC51: Expenses | AD51: G-cash | AE51: 3 | AF51: 2024 | AG51: Supa | AK51: 361 | AL51: 45471 | AM51: Supa | AN51: 125 | AO51: Expenses | AP51: G-cash | AQ51: 6 | AR51: 2024 | AS51: Supa | AW51: 361 | AX51: 45471 | AY51: Supa | AZ51: 125 | BA51: Expenses | BB51: G-cash | BC51: 6 | BD51: 2024 | BE51: Supa
M52: 204 | N52: 45337 | O52: Steam (vampire survivors) | P52: 144 | Q52: Expenses | R52: G-cash | S52: 2 | T52: 2024 | U52: steam | Y52: 232 | Z52: 45357 | AA52: Spotify | AB52: 239 | AC52: Expenses | AD52: G-cash | AE52: 3 | AF52: 2024 | AG52: Spotify | AK52: 378 | AL52: 45483 | AM52: supa | AN52: 50 | AO52: Expenses | AP52: G-cash | AQ52: 7 | AR52: 2024 | AS52: Supa | AW52: 378 | AX52: 45483 | AY52: supa | AZ52: 50 | BA52: Expenses | BB52: G-cash | BC52: 7 | BD52: 2024 | BE52: Supa
M53: 206 | N53: 45338 | O53: wifi load (family access) | P53: 199 | Q53: Expenses | R53: G-cash | S53: 2 | T53: 2024 | U53: wifi load (family access) | Y53: 237 | Z53: 45365 | AA53: wifi load (magic data) | AB53: 599 | AC53: Expenses | AD53: G-cash | AE53: 3 | AF53: 2024 | AG53: wifi load (magic data) | AK53: 379 | AL53: 45483 | AM53: supa | AN53: 125 | AO53: Expenses | AP53: G-cash | AQ53: 7 | AR53: 2024 | AS53: Supa | AW53: 379 | AX53: 45483 | AY53: supa | AZ53: 125 | BA53: Expenses | BB53: G-cash | BC53: 7 | BD53: 2024 | BE53: Supa
M54: 207 | N54: 45338 | O54: Steam (overcooked 2) | P54: 199 | Q54: Expenses | R54: G-cash | S54: 2 | T54: 2024 | U54: steam | Y54: 239 | Z54: 45373 | AA54: YT Membership | AB54: 129 | AC54: Expenses | AD54: G-cash | AE54: 3 | AF54: 2024 | AG54: YT Membership | AK54: 381 | AL54: 45485 | AM54: Supa | AN54: 50 | AO54: Expenses | AP54: G-cash | AQ54: 7 | AR54: 2024 | AS54: Supa | AW54: 381 | AX54: 45485 | AY54: Supa | AZ54: 50 | BA54: Expenses | BB54: G-cash | BC54: 7 | BD54: 2024 | BE54: Supa
M55: 209 | N55: 45343 | O55: Genshin Welkin | P55: 280 | Q55: Expenses | R55: G-cash | S55: 2 | T55: 2024 | U55: Genshin Welkin | Y55: 242 | Z55: 45374 | AA55: Genshin Welkin | AB55: 280 | AC55: Expenses | AD55: G-cash | AE55: 3 | AF55: 2024 | AG55: Genshin Welkin | AK55: 419 | AL55: 45503 | AM55: supa | AN55: 125 | AO55: Expenses | AP55: G-cash | AQ55: 7 | AR55: 2024 | AS55: Supa | AW55: 419 | AX55: 45503 | AY55: supa | AZ55: 125 | BA55: Expenses | BB55: G-cash | BC55: 7 | BD55: 2024 | BE55: Supa
M56: 210 | N56: 45344 | O56: Supa | P56: 129 | Q56: Expenses | R56: G-cash | S56: 2 | T56: 2024 | U56: Supa | Y56: 247 | Z56: 45378 | AA56: wifi load (family access) | AB56: 199 | AC56: Expenses | AD56: G-cash | AE56: 3 | AF56: 2024 | AG56: wifi load (family access) | AK56: 420 | AL56: 45503 | AM56: Supa | AN56: 125 | AO56: Expenses | AP56: G-cash | AQ56: 7 | AR56: 2024 | AS56: Supa | AW56: 420 | AX56: 45503 | AY56: Supa | AZ56: 125 | BA56: Expenses | BB56: G-cash | BC56: 7 | BD56: 2024 | BE56: Supa
M57: 223 | N57: 45353 | O57: Supa | P57: 125 | Q57: Expenses | R57: G-cash | S57: 3 | T57: 2024 | U57: Supa | Y57: 253 | Z57: 45384 | AA57: Supa | AB57: 50 | AC57: Expenses | AD57: G-cash | AE57: 4 | AF57: 2024 | AG57: Supa | AK57: 447 | AL57: 45519 | AM57: Supa | AN57: 125 | AO57: Expenses | AP57: G-cash | AQ57: 8 | AR57: 2024 | AS57: Supa | AW57: 447 | AX57: 45519 | AY57: Supa | AZ57: 125 | BA57: Expenses | BB57: G-cash | BC57: 8 | BD57: 2024 | BE57: Supa
M58: 230 | N58: 45356 | O58: Supa | P58: 50 | Q58: Expenses | R58: G-cash | S58: 3 | T58: 2024 | U58: Supa | Y58: 254 | Z58: 45387 | AA58: Supa | AB58: 125 | AC58: Expenses | AD58: G-cash | AE58: 4 | AF58: 2024 | AG58: Supa | AK58: 462 | AL58: 45539 | AM58: supa | AN58: 125 | AO58: Expenses | AP58: G-cash | AQ58: 9 | AR58: 2024 | AS58: Supa | AW58: 462 | AX58: 45539 | AY58: supa | AZ58: 125 | BA58: Expenses | BB58: G-cash | BC58: 9 | BD58: 2024 | BE58: Supa
... M68: 256 | N68: 45388 | O68: Spotify | P68: 239 | Q68: Expenses | R68: G-cash | S68: 4 | T68: 2024 | U68: Spotify | Y68: 283 | Z68: 45415 | AA68: wifi load (family access) | AB68: 199 | AC68: Expenses | AD68: G-cash | AE68: 5 | AF68: 2024 | AG68: wifi load (family access) | AK68: 534 | AL68: 45590 | AM68: Supa | AN68: 25 | AO68: Expenses | AP68: G-cash | AQ68: 10 | AR68: 2024 | AS68: Supa | AW68: 534 | AX68: 45590 | AY68: Supa | AZ68: 25 | BA68: Expenses | BB68: G-cash | BC68: 10 | BD68: 2024 | BE68: Supa
M69: 268 | N69: 45398 | O69: Supa | P69: 125 | Q69: Expenses | R69: G-cash | S69: 4 | T69: 2024 | U69: Supa | Y69: 290 | Z69: 45418 | AA69: Supa | AB69: 125 | AC69: Expenses | AD69: G-cash | AE69: 5 | AF69: 2024 | AG69: Supa
M70: 269 | N70: 45402 | O70: wifi load (magic data) | P70: 599 | Q70: Expenses | R70: G-cash | S70: 4 | T70: 2024 | U70: wifi load (magic data) | Y70: 291 | Z70: 45418 | AA70: Supa | AB70: 50 | AC70: Expenses | AD70: G-cash | AE70: 5 | AF70: 2024 | AG70: Supa
M71: 271 | N71: 45403 | O71: Genshin Welkin | P71: 280 | Q71: Expenses | R71: G-cash | S71: 4 | T71: 2024 | U71: Genshin Welkin | Y71: 292 | Z71: 45419 | AA71: Spotify | AB71: 239 | AC71: Expenses | AD71: G-cash | AE71: 5 | AF71: 2024 | AG71: Spotify
M72: 272 | N72: 45404 | O72: YT Membership | P72: 129 | Q72: Expenses | R72: G-cash | S72: 4 | T72: 2024 | U72: YT Membership | Y72: 298 | Z72: 45425 | AA72: mobile load (magic data) | AB72: 399 | AC72: Expenses | AD72: G-cash | AE72: 5 | AF72: 2024 | AG72: mobile load (magic data)
M73: 273 | N73: 45404 | O73: wifi load (family access) | P73: 199 | Q73: Expenses | R73: G-cash | S73: 4 | T73: 2024 | U73: wifi load (family access) | Y73: 302 | Z73: 45430 | AA73: Supa | AB73: 50 | AC73: Expenses | AD73: G-cash | AE73: 5 | AF73: 2024 | AG73: Supa
M74: 274 | N74: 45412 | O74: Palaman peanut | P74: 500 | Q74: Expenses | R74: G-cash | S74: 4 | T74: 2024 | U74: Palaman peanut | Y74: 303 | Z74: 45434 | AA74: YT Membership | AB74: 129 | AC74: Expenses | AD74: G-cash | AE74: 5 | AF74: 2024 | AG74: YT Membership
M75: 281 | N75: 45415 | O75: Supa | P75: 50 | Q75: Expenses | R75: G-cash | S75: 5 | T75: 2024 | U75: Supa | Y75: 304 | Z75: 45434 | AA75: Genshin Welkin | AB75: 280 | AC75: Expenses | AD75: G-cash | AE75: 5 | AF75: 2024 | AG75: Genshin Welkin
M76: 282 | N76: 45415 | O76: Supa | P76: 125 | Q76: Expenses | R76: G-cash | S76: 5 | T76: 2024 | U76: Supa | Y76: 307 | Z76: 45435 | AA76: wifi load (family access) | AB76: 199 | AC76: Expenses | AD76: G-cash | AE76: 5 | AF76: 2024 | AG76: wifi load (family access)
M77: 283 | N77: 45415 | O77: wifi load (family access) | P77: 199 | Q77: Expenses | R77: G-cash | S77: 5 | T77: 2024 | U77: wifi load (family access) | Y77: 310 | Z77: 45440 | AA77: Supa | AB77: 125 | AC77: Expenses | AD77: G-cash | AE77: 5 | AF77: 2024 | AG77: Supa
M78: 289 | N78: 45416 | O78: Gcash cash-in | P78: 3000 | Q78: Deposit | R78: G-cash | S78: 5 | T78: 2024 | U78: Gcash cash-in | Y78: 313 | Z78: 45447 | AA78: Supa | AB78: 125 | AC78: Expenses | AD78: G-cash | AE78: 6 | AF78: 2024 | AG78: Supa
M79: 290 | N79: 45418 | O79: Supa | P79: 125 | Q79: Expenses | R79: G-cash | S79: 5 | T79: 2024 | U79: Supa | Y79: 314 | Z79: 45448 | AA79: wifi load (magic data) | AB79: 699 | AC79: Expenses | AD79: G-cash | AE79: 6 | AF79: 2024 | AG79: wifi load (magic data)
M80: 291 | N80: 45418 | O80: Supa | P80: 50 | Q80: Expenses | R80: G-cash | S80: 5 | T80: 2024 | U80: Supa | Y80: 315 | Z80: 45449 | AA80: Supa | AB80: 125 | AC80: Expenses | AD80: G-cash | AE80: 6 | AF80: 2024 | AG80: Supa
... M140: 485 | N140: 45555 | O140: wifi load (magic data) | P140: 700 | Q140: Expenses | R140: G-cash | S140: 9 | T140: 2024 | U140: wifi load (magic data) | Y140: 542 | Z140: 45599 | AA140: wifi load (family access) | AB140: 199 | AC140: Expenses | AD140: G-cash | AE140: 11 | AF140: 2024 | AG140: wifi load (family access)
M141: 486 | N141: 45555 | O141: wifi load (family access) | P141: 200 | Q141: Expenses | R141: G-cash | S141: 9 | T141: 2024 | U141: wifi load (family access)
M142: 491 | N142: 45557 | O142: YT Membership | P142: 129 | Q142: Expenses | R142: G-cash | S142: 9 | T142: 2024 | U142: YT Membership
M143: 495 | N143: 45562 | O143: aragmot (teachers day) | P143: 500 | Q143: Deposit | R143: G-cash | S143: 9 | T143: 2024 | U143: aragmot
M144: 504 | N144: 45569 | O144: aragmot (teachers day) | P144: 855 | Q144: Deposit | R144: G-cash | S144: 10 | T144: 2024 | U144: aragmot
M145: 510 | N145: 45570 | O145: supa | P145: 125 | Q145: Expenses | R145: G-cash | S145: 10 | T145: 2024 | U145: Supa
M146: 511 | N146: 45570 | O146: Supa | P146: 50 | Q146: Expenses | R146: G-cash | S146: 10 | T146: 2024 | U146: Supa
M147: 512 | N147: 45571 | O147: Spotify | P147: 239 | Q147: Expenses | R147: G-cash | S147: 10 | T147: 2024 | U147: Spotify
M148: 515 | N148: 45575 | O148: wifi load (family access) | P148: 199 | Q148: Expenses | R148: G-cash | S148: 10 | T148: 2024 | U148: wifi load (family access)
M149: 525 | N149: 45581 | O149: supa | P149: 125 | Q149: Expenses | R149: G-cash | S149: 10 | T149: 2024 | U149: Supa
M150: 526 | N150: 45583 | O150: wifi load (family access) | P150: 199 | Q150: Expenses | R150: G-cash | S150: 10 | T150: 2024 | U150: wifi load (family access)
M151: 527 | N151: 45584 | O151: Supa | P151: 125 | Q151: Expenses | R151: G-cash | S151: 10 | T151: 2024 | U151: Supa
M152: 529 | N152: 45587 | O152: YT Membership | P152: 129 | Q152: Expenses | R152: G-cash | S152: 10 | T152: 2024 | U152: YT Membership
... M158: 542 | N158: 45599 | O158: wifi load (family access) | P158: 199 | Q158: Expenses | R158: G-cash | S158: 11 | T158: 2024 | U158: wifi load (family access)

Sheet cleaned_source_dataset
A1: Navigate: | B1: Dashboard | C1: Findings | D1: Pivot & Derived Tables | E1: Analysis & Diagnosis | F1: Data Visualization | G1: Cleaned Data Source | H1: Raw Data Source
A2: trans_no | B2: date | C2: details | D2: amount | E2: transaction | F2: transaction_mode | G2: month | H2: year | I2: cleaned_detail
A3: 1 | B3: 45183 | C3: サラリー | D3: 17732 | E3: Income | F3: Bank | G3: =MONTH(cleaned_personal_finance_data[[#This Row],[date]]) -> 9 | H3: =YEAR(cleaned_personal_finance_data[[#This Row],[date]]) -> 2023 | I3: salary
A4: 2 | B4: 45208 | C4: サラリー | D4: 12754 | E4: Income | F4: Bank | G4: =MONTH(cleaned_personal_finance_data[[#This Row],[date]]) -> 10 | H4: =YEAR(cleaned_personal_finance_data[[#This Row],[date]]) -> 2023 | I4: salary
A5: 3 | B5: 45214 | C5: bank withdraw | D5: 26142 | E5: Withdraw | F5: Bank | G5: =MONTH(cleaned_personal_finance_data[[#This Row],[date]]) -> 10 | H5: =YEAR(cleaned_personal_finance_data[[#This Row],[date]]) -> 2023 | I5: bank withdraw
A6: 4 | B6: 45214 | C6: stash deposit | D6: 26142 | E6: Deposit | F6: Stash | G6: =MONTH(cleaned_personal_finance_data[[#This Row],[date]]) -> 10 | H6: =YEAR(cleaned_personal_finance_data[[#This Row],[date]]) -> 2023 | I6: stash deposit
A7: 5 | B7: 45230 | C7: サラリー | D7: 12834 | E7: Income | F7: Bank | G7: =MONTH(cleaned_personal_finance_data[[#This Row],[date]]) -> 10 | H7: =YEAR(cleaned_personal_finance_data[[#This Row],[date]]) -> 2023 | I7: salary
A8: 6 | B8: 45235 | C8: Monthly gasoline (oct) | D8: 2550 | E8: Expenses | F8: Stash | G8: =MONTH(cleaned_personal_finance_data[[#This Row],[date]]) -> 11 | H8: =YEAR(cleaned_personal_finance_data[[#This Row],[date]]) -> 2023 | I8: Gasolina
A9: 7 | B9: 45235 | C9: Balay (Oct) | D9: 5000 | E9: Expenses | F9: Stash | G9: =MONTH(cleaned_personal_finance_data[[#This Row],[date]]) -> 11 | H9: =YEAR(cleaned_personal_finance_data[[#This Row],[date]]) -> 2023 | I9: balay
A10: 8 | B10: 45235 | C10: Tahong harvest | D10: 12560 | E10: Income | F10: Stash | G10: =MONTH(cleaned_personal_finance_data[[#This Row],[date]]) -> 11 | H10: =YEAR(cleaned_personal_finance_data[[#This Row],[date]]) -> 2023 | I10: Tahong harvest
A11: 9 | B11: 45235 | C11: pansit canton | D11: 56 | E11: Expenses | F11: Stash | G11: =MONTH(cleaned_personal_finance_data[[#This Row],[date]]) -> 11 | H11: =YEAR(cleaned_personal_finance_data[[#This Row],[date]]) -> 2023 | I11: pansit canton
A12: 10 | B12: 45235 | C12: monay | D12: 30 | E12: Expenses | F12: Stash | G12: =MONTH(cleaned_personal_finance_data[[#This Row],[date]]) -> 11 | H12: =YEAR(cleaned_personal_finance_data[[#This Row],[date]]) -> 2023 | I12: Monay (1 putos)
A13: 11 | B13: 45235 | C13: Gcash cash-in | D13: 2010 | E13: Withdraw | F13: Stash | G13: =MONTH(cleaned_personal_finance_data[[#This Row],[date]]) -> 11 | H13: =YEAR(cleaned_personal_finance_data[[#This Row],[date]]) -> 2023 | I13: Gcash cash-in
A14: 12 | B14: 45235 | C14: Gcash cash-in | D14: 2010 | E14: Deposit | F14: G-cash | G14: =MONTH(cleaned_personal_finance_data[[#This Row],[date]]) -> 11 | H14: =YEAR(cleaned_personal_finance_data[[#This Row],[date]]) -> 2023 | I14: Gcash cash-in
... A673: 671 | B673: 45687 | C673: サラリー | D673: 13202 | E673: Income | F673: Bank | G673: =MONTH(cleaned_personal_finance_data[[#This Row],[date]]) -> 1 | H673: =YEAR(cleaned_personal_finance_data[[#This Row],[date]]) -> 2025 | I673: salary

Sheet personal_finance_data
A1: Navigate: | B1: Dashboard | C1: Findings | D1: Pivot & Derived Tables | E1: Analysis & Diagnosis | F1: Data Visualization | G1: Cleaned Data Source | H1: Raw Data Source
A2: trans_no | B2: date | C2: details | D2: amount | E2: transaction | F2: transaction_mode
A3: 1 | B3: 45183 | C3: サラリー | D3: 17732 | E3: Income | F3: Bank
A4: 2 | B4: 45208 | C4: サラリー | D4: 12754 | E4: Income | F4: Bank
A5: 3 | B5: 45214 | C5: bank withdraw | D5: 26142 | E5: Withdraw | F5: Bank
A6: 4 | B6: 45214 | C6: stash deposit | D6: 26142 | E6: Deposit | F6: Stash
A7: 5 | B7: 45230 | C7: サラリー | D7: 12834 | E7: Income | F7: Bank
A8: 6 | B8: 45235 | C8: Monthly gasoline (oct) | D8: 2550 | E8: Expenses | F8: Stash
A9: 7 | B9: 45235 | C9: Balay (Oct) | D9: 5000 | E9: Expenses | F9: Stash
A10: 8 | B10: 45235 | C10: Tahong harvest | D10: 12560 | E10: Income | F10: Stash
A11: 9 | B11: 45235 | C11: pansit canton | D11: 56 | E11: Expenses | F11: Stash
A12: 10 | B12: 45235 | C12: monay | D12: 30 | E12: Expenses | F12: Stash
A13: 11 | B13: 45235 | C13: Gcash cash-in | D13: 2010 | E13: Withdraw | F13: Stash
A14: 12 | B14: 45235 | C14: Gcash cash-in | D14: 2010 | E14: Deposit | F14: G-cash
... A673: 671 | B673: 45687 | C673: サラリー | D673: 13202 | E673: Income | F673: Bank
